Workbook
Name USD: [1]SUMMARY!#REF!
Name 슬라이서_Parts: #N/A
Name 슬라이서_Shuttle: #N/A

Sheet Parts
A1: PARTS LIST | G1: 안전재고 | H1: 전체 ITEM | I1: 안전재고 부족 | J1: Safety Stock Fulfillment Rate
G2: ASRS | H2: =COUNTIFS(A:A,G2) -> 349 | I2: =COUNTIFS(A:A,G2,J:J,"X") -> 1 | J2: =(H2-I2)/H2 -> 0.99713467
G3: CONVEYOR | H3: =COUNTIFS(A:A,G3) -> 703 | I3: =COUNTIFS(A:A,G3,J:J,"X") -> 33 | J3: =(H3-I3)/H3 -> 0.95305832
G4: UTILITY | H4: =COUNTIFS(A:A,G4) -> 192 | I4: =COUNTIFS(A:A,G4,J:J,"X") -> 7 | J4: =(H4-I4)/H4 -> 0.96354167 | AB4: 입력날짜 | AC4: 45961 | AD4: 45989 | AE4: 46022 | AF4: 45687 | AG4: 46080 | AH4: 46112
G5: ELECTRICAL | H5: =COUNTIFS(A:A,G5) -> 71 | I5: =COUNTIFS(A:A,G5,J:J,"X") -> 0 | J5: =(H5-I5)/H5 -> 1 | P5: 1712 | AC5: FY26 | AK5: FY27 | AL5: FY27 | AM5: FY27 | AN5: FY27 | AO5: FY27 | AP5: FY27 | AQ5: FY27 | AR5: FY27 | AS5: FY27 | AT5: FY27 | AU5: FY27 | AV5: FY27
A6: EQUIPMENT | B6: Hierarchy-1 | C6: Hierarchy-2 | D6: Hierarchy-3 | E6: Hierarchy-4 | F6: 설치설비 | G6: 설치갯수 | H6: 현재재고 | I6: 안전재고 | J6: 안전재고 충족현황 | K6: 보관 위치 | L6: Supplier | M6: 제조사 | N6: Order number | O6: Unit price (EUR) | P6: Unit price (KRW) | Q6: Life time | R6: Lead time | S6: Criticality | T6: Demend per year | U6: 입고예정 | V6: 입고 후 총 수량 | W6: 2차분 입고수량 | X6: 기존수량+입고수량 | AC6: Oct | AD6: Nov | AE6: Dec | AF6: Jan | AG6: Feb | AH6: Mar | AI6: Apr | AJ6: May | AK6: Jun | AL6: Jul | AM6: Aug | AN6: Sep | AO6: Oct | AP6: Nov | AQ6: Dec | AR6: Jan | AS6: Feb | AT6: Mar | AU6: Apr | AV6: May | AW6: Jun | AX6: Jul | AY6: Aug | AZ6: Sep | BA6: Oct | BB6: Nov | BC6: Dec | BD6: Jan | BE6: Feb | BF6: Mar | BG6: Apr | BH6: May
A7: Conveyor | B7: KNAPP Conveyor | C7: Motorized roller | D7: NB=660 EC5000 18:1 P... | E7: EL 660, RL:646mm | F7: WE01, WE02, WA01, WA02, TK01, TK03 | G7: 56 | H7: 3 | I7: =MIN(10,MAX(1,ROUNDUP(IFERROR(IF(OR(G7="",G7=0),1,G7),1)*0.1*90/365,0))) -> 2 | J7: =IF(H7<I7,"X","O") -> O | K7: C14 | M7: Interoll | N7: 10325252_01_0004 | W7: =_xlfn.XLOOKUP(N7,#REF!,#REF!,"없음") -> #REF! | Y7: =_xlfn.XLOOKUP(N7,#REF!,#REF!,"없음") -> #REF! | AA7: % | AB7: ASRS | AC7: 0.88554217 | AD7: 0.88554217 | AE7: 0.91 | AF7: 0.9 | AG7: 0.97
A8: Conveyor | B8: KNAPP Conveyor | C8: Motorized roller | D8: NB=900 EC5000 18:1 P... | E8: EL 900, RL:886mm | F8: WE01, WE02, WA02, TK01, TK03 | G8: 50 | H8: 2 | I8: =MIN(10,MAX(1,ROUNDUP(IFERROR(IF(OR(G8="",G8=0),1,G8),1)*0.1*90/365,0))) -> 2 | J8: =IF(H8<I8,"X","O") -> O | K8: C14 | M8: Interoll | N8: 10325252_01_0027 | W8: =_xlfn.XLOOKUP(N8,#REF!,#REF!,"없음") -> #REF! | Y8: =_xlfn.XLOOKUP(N8,#REF!,#REF!,"없음") -> #REF! | AA8: % | AB8: CONVEYOR | AC8: 0.73940345 | AD8: 0.83832335 | AE8: 0.91 | AF8: 0.95 | AG8: 0.95
A9: Conveyor | B9: KNAPP Conveyor | C9: Motorized roller | D9: NB1=660 EC5000 13:1 ... | E9: EL 660 | F9: WE01 | G9: 5 | H9: 3 | I9: =MIN(10,MAX(1,ROUNDUP(IFERROR(IF(OR(G9="",G9=0),1,G9),1)*0.1*90/365,0))) -> 1 | J9: =IF(H9<I9,"X","O") -> O | K9: C14 | M9: Interoll | N9: 10327146_01_0002 | W9: =_xlfn.XLOOKUP(N9,#REF!,#REF!,"없음") -> #REF! | Y9: =_xlfn.XLOOKUP(N9,#REF!,#REF!,"없음") -> #REF! | AA9: % | AB9: UTILITY | AC9: 1 | AD9: 1 | AE9: 0.98 | AF9: 0.98 | AG9: 0.98
A10: Conveyor | B10: KNAPP Conveyor | C10: Motorized roller | D10: 746 EC5000 35W 18:1 / EC310 30/22 16:1 62421074/0017 | E10: RL:736mm | G10: 76 | H10: 2 | I10: =MIN(10,MAX(1,ROUNDUP(IFERROR(IF(OR(G10="",G10=0),1,G10),1)*0.1*90/365,0))) -> 2 | J10: =IF(H10<I10,"X","O") -> O | K10: C14 | M10: Interoll | N10: 10805810_01_0044 | W10: =_xlfn.XLOOKUP(N10,#REF!,#REF!,"없음") -> #REF! | Y10: =_xlfn.XLOOKUP(N10,#REF!,#REF!,"없음") -> #REF! | AA10: % | AB10: ELECTRICAL | AC10: 1 | AD10: 1 | AE10: 1 | AF10: 1 | AG10: 1
A11: Conveyor | B11: KNAPP Conveyor | C11: Motorized roller | D11: 746 50 ST 18:1 PV EC5000 | E11: RL:736mm | G11: 51 | H11: 2 | I11: =MIN(10,MAX(1,ROUNDUP(IFERROR(IF(OR(G11="",G11=0),1,G11),1)*0.1*90/365,0))) -> 2 | J11: =IF(H11<I11,"X","O") -> O | K11: C14 | M11: Interoll | N11: 10661784_01_0044 | W11: =_xlfn.XLOOKUP(N11,#REF!,#REF!,"없음") -> #REF! | Y11: =_xlfn.XLOOKUP(N11,#REF!,#REF!,"없음") -> #REF! | AA11: Total item | AB11: ASRS | AC11: 332 | AD11: 332 | AE11: 344 | AF11: 346 | AG11: 346
A12: Conveyor | B12: KNAPP Conveyor | C12: Motorized roller | D12: NB=750 EC310 16-1 PV / EC5000 35W A1 18:1 TYPE2 DE01339523 | E12: Taper, RL:736mm, 검정색 | G12: 42 | H12: 2 | I12: =MIN(10,MAX(1,ROUNDUP(IFERROR(IF(OR(G12="",G12=0),1,G12),1)*0.1*90/365,0))) -> 2 | J12: =IF(H12<I12,"X","O") -> O | K12: C14 | M12: Interoll | N12: 10330501_01_0010 | W12: =_xlfn.XLOOKUP(N12,#REF!,#REF!,"없음") -> #REF! | Y12: =_xlfn.XLOOKUP(N12,#REF!,#REF!,"없음") -> #REF! | AA12: Total item | AB12: CONVEYOR | AC12: 637 | AD12: 668 | AE12: 671 | AF12: 702 | AG12: 703
A13: Conveyor | B13: KNAPP Conveyor | C13: Motorized roller | D13: 716 EC5000 35W 18:1 | E13: RL:706mm | G13: 19 | H13: 2 | I13: =MIN(10,MAX(1,ROUNDUP(IFERROR(IF(OR(G13="",G13=0),1,G13),1)*0.1*90/365,0))) -> 1 | J13: =IF(H13<I13,"X","O") -> O | K13: C14 | M13: Interoll | N13: 10805810_01_0042 | W13: =_xlfn.XLOOKUP(N13,#REF!,#REF!,"없음") -> #REF! | Y13: =_xlfn.XLOOKUP(N13,#REF!,#REF!,"없음") -> #REF! | AA13: Total item | AB13: UTILITY | AC13: 179 | AD13: 179 | AE13: 192 | AF13: 192 | AG13: 192
A14: Conveyor | B14: KNAPP Conveyor | C14: Motorized roller | D14: 296 50 ST 13:1 PV EC... | E14: 296 | F14: WE01, WE02 | G14: 4 | H14: 2 | I14: =MIN(10,MAX(1,ROUNDUP(IFERROR(IF(OR(G14="",G14=0),1,G14),1)*0.1*90/365,0))) -> 1 | J14: =IF(H14<I14,"X","O") -> O | K14: C13 | M14: Interoll | N14: 10661659_01_0003 | W14: =_xlfn.XLOOKUP(N14,#REF!,#REF!,"없음") -> #REF! | Y14: =_xlfn.XLOOKUP(N14,#REF!,#REF!,"없음") -> #REF! | AA14: Total item | AB14: ELECTRICAL | AC14: 71 | AD14: 71 | AE14: 71 | AF14: 71 | AG14: 71
A15: Conveyor | B15: KNAPP Conveyor | C15: Motorized roller | D15: 326 50 ST 13:1 PV EC5000 | E15: 326, RL:316mm | F15: WE01, WE02, WA02, WA03 | G15: 10 | H15: 3 | I15: =MIN(10,MAX(1,ROUNDUP(IFERROR(IF(OR(G15="",G15=0),1,G15),1)*0.1*90/365,0))) -> 1 | J15: =IF(H15<I15,"X","O") -> O | K15: C13 | M15: Interoll | N15: 10661659_01_0005 | W15: =_xlfn.XLOOKUP(N15,#REF!,#REF!,"없음") -> #REF! | Y15: =_xlfn.XLOOKUP(N15,#REF!,#REF!,"없음") -> #REF! | AA15: 부족 | AB15: ASRS | AC15: 38 | AD15: 38 | AE15: 32 | AF15: 35 | AG15: 10
A16: Conveyor | B16: KNAPP Conveyor | C16: Motorized roller | D16: 626 50 ST 13:1 PV EC... | E16: 626 | F16: WE01 | G16: 1 | H16: 1 | I16: =MIN(10,MAX(1,ROUNDUP(IFERROR(IF(OR(G16="",G16=0),1,G16),1)*0.1*90/365,0))) -> 1 | J16: =IF(H16<I16,"X","O") -> O | K16: C14 | M16: Interoll | N16: 10661659_01_0034 | W16: =_xlfn.XLOOKUP(N16,#REF!,#REF!,"없음") -> #REF! | Y16: =_xlfn.XLOOKUP(N16,#REF!,#REF!,"없음") -> #REF! | AA16: 부족 | AB16: CONVEYOR | AC16: 166 | AD16: 108 | AE16: 60 | AF16: 38 | AG16: 34
A17: Conveyor | B17: KNAPP Conveyor | C17: Motorized roller | D17: 656 50 ST 13:1 PV EC5000 | E17: 656, RL:646mm | F17: WE01, WE02, WA01, WA02 | G17: 21 | H17: 3 | I17: =MIN(10,MAX(1,ROUNDUP(IFERROR(IF(OR(G17="",G17=0),1,G17),1)*0.1*90/365,0))) -> 1 | J17: =IF(H17<I17,"X","O") -> O | K17: C14 | M17: Interoll | N17: 10661659_01_0038 | W17: =_xlfn.XLOOKUP(N17,#REF!,#REF!,"없음") -> #REF! | Y17: =_xlfn.XLOOKUP(N17,#REF!,#REF!,"없음") -> #REF! | AA17: 부족 | AB17: UTILITY | AC17: 0 | AD17: 0 | AE17: 3 | AF17: 3 | AG17: 3
A18: Conveyor | B18: KNAPP Conveyor | C18: Motorized roller | D18: 656 50 ST 13:1 PV GU... | E18: 656 | F18: WE01 | G18: 5 | H18: 1 | I18: =MIN(10,MAX(1,ROUNDUP(IFERROR(IF(OR(G18="",G18=0),1,G18),1)*0.1*90/365,0))) -> 1 | J18: =IF(H18<I18,"X","O") -> O | K18: C14 | M18: Interoll | N18: 10661780_01_0027 | W18: =_xlfn.XLOOKUP(N18,#REF!,#REF!,"없음") -> #REF! | Y18: =_xlfn.XLOOKUP(N18,#REF!,#REF!,"없음") -> #REF! | AA18: 부족 | AB18: ELECTRICAL | AC18: 0 | AD18: 0 | AE18: 0 | AF18: 0 | AG18: 0
A19: Conveyor | B19: KNAPP Conveyor | C19: Motorized roller | D19: 266 50 ST 18:1 PV EC5000 | E19: 266, RL:256mm | F19: WE01, WE02, WA01, WA02, WA03, TK01, TK02, TK03 | G19: 54 | H19: 3 | I19: =MIN(10,MAX(1,ROUNDUP(IFERROR(IF(OR(G19="",G19=0),1,G19),1)*0.1*90/365,0))) -> 2 | J19: =IF(H19<I19,"X","O") -> O | K19: C13 | M19: Interoll | N19: 10661784_01_0001 | W19: =_xlfn.XLOOKUP(N19,#REF!,#REF!,"없음") -> #REF! | Y19: =_xlfn.XLOOKUP(N19,#REF!,#REF!,"없음") -> #REF!
A20: Conveyor | B20: KNAPP Conveyor | C20: Motorized roller | D20: 626 50 ST 18:1 PV EC5000 | E20: 626, RL:616mm | F20: WE01, WE02, WA01, WA02, TK01, TK03 | G20: 47 | H20: 3 | I20: =MIN(10,MAX(1,ROUNDUP(IFERROR(IF(OR(G20="",G20=0),1,G20),1)*0.1*90/365,0))) -> 2 | J20: =IF(H20<I20,"X","O") -> O | K20: C14 | M20: Interoll | N20: 10661784_01_0034 | W20: =_xlfn.XLOOKUP(N20,#REF!,#REF!,"없음") -> #REF! | Y20: =_xlfn.XLOOKUP(N20,#REF!,#REF!,"없음") -> #REF!
A21: Conveyor | B21: KNAPP Conveyor | C21: Motorized roller | D21: 656 50 ST 18:1 PV EC5000 | E21: 656, RL:646mm | F21: WE01, WE02, WA01, WA02, TK01, TK03 | G21: 100 | H21: 3 | I21: =MIN(10,MAX(1,ROUNDUP(IFERROR(IF(OR(G21="",G21=0),1,G21),1)*0.1*90/365,0))) -> 3 | J21: =IF(H21<I21,"X","O") -> O | K21: C14 | M21: Interoll | N21: 10661784_01_0038 | W21: =_xlfn.XLOOKUP(N21,#REF!,#REF!,"없음") -> #REF! | Y21: =_xlfn.XLOOKUP(N21,#REF!,#REF!,"없음") -> #REF!
A22: Conveyor | B22: KNAPP Conveyor | C22: Motorized roller | D22: 896 50 ST 18:1 PV EC5000 | E22: 896, RL:886mm | F22: WE01, WE02, WA02, TK01, TK03 | G22: 72 | H22: 6 | I22: =MIN(10,MAX(1,ROUNDUP(IFERROR(IF(OR(G22="",G22=0),1,G22),1)*0.1*90/365,0))) -> 2 | J22: =IF(H22<I22,"X","O") -> O | K22: C14 | M22: Interoll | N22: 10661784_01_0054 | W22: =_xlfn.XLOOKUP(N22,#REF!,#REF!,"없음") -> #REF! | Y22: =_xlfn.XLOOKUP(N22,#REF!,#REF!,"없음") -> #REF!
A23: Conveyor | B23: KNAPP Conveyor | C23: Motorized roller | D23: 656 50 ST 18:1 PV GU... / EC5000 35W A1 18:1 TYPE2 48/24 DE1397590 | E23: 656 | F23: WE01, WA01, TK01, TK03 | G23: 9 | H23: 8 | I23: =MIN(10,MAX(1,ROUNDUP(IFERROR(IF(OR(G23="",G23=0),1,G23),1)*0.1*90/365,0))) -> 1 | J23: =IF(H23<I23,"X","O") -> O | K23: A21 | M23: Interoll | N23: 10661785_01_0027 | W23: =_xlfn.XLOOKUP(N23,#REF!,#REF!,"없음") -> #REF! | Y23: =_xlfn.XLOOKUP(N23,#REF!,#REF!,"없음") -> #REF!
A24: Conveyor | B24: KNAPP Conveyor | C24: Motorized roller | D24: 656 50 ST 13:1 PV KO... | E24: Taper ,656 | F24: WE01, WA02 | G24: 3 | H24: 2 | I24: =MIN(10,MAX(1,ROUNDUP(IFERROR(IF(OR(G24="",G24=0),1,G24),1)*0.1*90/365,0))) -> 1 | J24: =IF(H24<I24,"X","O") -> O | K24: C14 | M24: Interoll | N24: 10661867_01_0008 | W24: =_xlfn.XLOOKUP(N24,#REF!,#REF!,"없음") -> #REF! | Y24: =_xlfn.XLOOKUP(N24,#REF!,#REF!,"없음") -> #REF!
A25: Conveyor | B25: KNAPP Conveyor | C25: Motorized roller | D25: 656 50 ST 18:1 PV KO... / EC5000 35W A1 18:1 TYPE2 T 47/24 DE01390941 | E25: Taper, 656, RL:646mm | F25: WE01, WE02, WA01, WA02, TK01, TK03 | G25: 9 | H25: 2 | I25: =MIN(10,MAX(1,ROUNDUP(IFERROR(IF(OR(G25="",G25=0),1,G25),1)*0.1*90/365,0))) -> 1 | J25: =IF(H25<I25,"X","O") -> O | K25: C14 | M25: Interoll | N25: 10661869_01_0008 | W25: =_xlfn.XLOOKUP(N25,#REF!,#REF!,"없음") -> #REF! | Y25: =_xlfn.XLOOKUP(N25,#REF!,#REF!,"없음") -> #REF!
A26: Conveyor | B26: KNAPP Conveyor | C26: Motorized roller | D26: 866 50 ST 18:1 PV EC5000 | E26: 866, RL:656mm | F26: WE02, TK01, TK03 | G26: 34 | H26: 3 | I26: =MIN(10,MAX(1,ROUNDUP(IFERROR(IF(OR(G26="",G26=0),1,G26),1)*0.1*90/365,0))) -> 1 | J26: =IF(H26<I26,"X","O") -> O | K26: C14 | M26: Interoll | N26: 10661784_01_0052 | W26: =_xlfn.XLOOKUP(N26,#REF!,#REF!,"없음") -> #REF! | Y26: =_xlfn.XLOOKUP(N26,#REF!,#REF!,"없음") -> #REF!
A27: Conveyor | B27: KNAPP Conveyor | C27: Motorized roller | D27: NB=840 EC5000 18:1 P... | E27: 840 | F27: WA01 | G27: 1 | H27: 1 | I27: =MIN(10,MAX(1,ROUNDUP(IFERROR(IF(OR(G27="",G27=0),1,G27),1)*0.1*90/365,0))) -> 1 | J27: =IF(H27<I27,"X","O") -> O | K27: C14 | M27: Interoll | N27: 10325252_01_0010 | W27: =_xlfn.XLOOKUP(N27,#REF!,#REF!,"없음") -> #REF! | Y27: =_xlfn.XLOOKUP(N27,#REF!,#REF!,"없음") -> #REF!
A28: Conveyor | B28: KNAPP Conveyor | C28: Motorized roller | D28: 266 50 ST 13:1 PV EC... | E28: 266 | F28: WA01 | G28: 2 | H28: 2 | I28: =MIN(10,MAX(1,ROUNDUP(IFERROR(IF(OR(G28="",G28=0),1,G28),1)*0.1*90/365,0))) -> 1 | J28: =IF(H28<I28,"X","O") -> O | K28: C13 | M28: Interoll | N28: 10661659_01_0001 | W28: =_xlfn.XLOOKUP(N28,#REF!,#REF!,"없음") -> #REF! | Y28: =_xlfn.XLOOKUP(N28,#REF!,#REF!,"없음") -> #REF!
A29: Conveyor | B29: KNAPP Conveyor | C29: Motorized roller | D29: 836 50 ST 18:1 PV EC... | E29: 836 | F29: WA01 | G29: 1 | H29: 1 | I29: =MIN(10,MAX(1,ROUNDUP(IFERROR(IF(OR(G29="",G29=0),1,G29),1)*0.1*90/365,0))) -> 1 | J29: =IF(H29<I29,"X","O") -> O | K29: C14 | M29: Interoll | N29: 10661784_01_0050 | W29: =_xlfn.XLOOKUP(N29,#REF!,#REF!,"없음") -> #REF! | Y29: =_xlfn.XLOOKUP(N29,#REF!,#REF!,"없음") -> #REF!
A30: Conveyor | B30: KNAPP Conveyor | C30: Motorized roller | D30: NB=900 Int MR -M, ST... | E30: 900 | F30: TK01 | G30: 8 | H30: 10 | I30: =MIN(10,MAX(1,ROUNDUP(IFERROR(IF(OR(G30="",G30=0),1,G30),1)*0.1*90/365,0))) -> 1 | J30: =IF(H30<I30,"X","O") -> O | K30: 0 | M30: Interoll | N30: 10328021_02_0017 | W30: =_xlfn.XLOOKUP(N30,#REF!,#REF!,"없음") -> #REF! | Y30: =_xlfn.XLOOKUP(N30,#REF!,#REF!,"없음") -> #REF!
A31: Conveyor | B31: KNAPP Conveyor | C31: Motorized roller | D31: 956 50 ST 18:1 PV EC... | E31: 956 | F31: TK01 | G31: 1 | H31: 1 | I31: =MIN(10,MAX(1,ROUNDUP(IFERROR(IF(OR(G31="",G31=0),1,G31),1)*0.1*90/365,0))) -> 1 | J31: =IF(H31<I31,"X","O") -> O | K31: C14 | M31: Interoll | N31: 10661784_01_0058 | W31: =_xlfn.XLOOKUP(N31,#REF!,#REF!,"없음") -> #REF! | Y31: =_xlfn.XLOOKUP(N31,#REF!,#REF!,"없음") -> #REF!
A32: Conveyor | B32: KNAPP Conveyor | C32: Motorized roller | D32: 846 50 ST 18:1 PV EC5000 | E32: 846, RL:836mm | F32: SH01, SH02 | G32: 65 | H32: 3 | I32: 5 | J32: =IF(H32<I32,"X","O") -> X | K32: C14 | M32: Interoll | N32: 10661784_01_0051 | W32: =_xlfn.XLOOKUP(N32,#REF!,#REF!,"없음") -> #REF! | Y32: =_xlfn.XLOOKUP(N32,#REF!,#REF!,"없음") -> #REF!
A33: Conveyor | B33: KNAPP Conveyor | C33: Motorized roller | D33: 921 50 ST 18:1 PV EC5000 | E33: 921, RL:912mm | F33: SH01, SH02 | G33: 177 | H33: 3 | I33: =MIN(10,MAX(1,ROUNDUP(IFERROR(IF(OR(G33="",G33=0),1,G33),1)*0.1*90/365,0))) -> 5 | J33: =IF(H33<I33,"X","O") -> X | K33: C14 | M33: Interoll | N33: 10661784_01_0055 | W33: =_xlfn.XLOOKUP(N33,#REF!,#REF!,"없음") -> #REF! | Y33: =_xlfn.XLOOKUP(N33,#REF!,#REF!,"없음") -> #REF!
A34: Conveyor | B34: KNAPP Conveyor | C34: Motorized roller mounting plate | D34: Right side | E34: 파워롤러 서포트 | H34: 1 | I34: =MIN(10,MAX(1,ROUNDUP(IFERROR(IF(OR(G34="",G34=0),1,G34),1)*0.1*90/365,0))) -> 1 | J34: =IF(H34<I34,"X","O") -> O | K34: A22 | L34: KNAPP | M34: KNAPP | N34: 10324754_02 | W34: =_xlfn.XLOOKUP(N34,#REF!,#REF!,"없음") -> #REF! | Y34: =_xlfn.XLOOKUP(N34,#REF!,#REF!,"없음") -> #REF!
A35: Conveyor | B35: KNAPP Conveyor | C35: Motorized roller mounting plate | D35: Left side | E35: 파워롤러 서포트 | H35: 3 | I35: =MIN(10,MAX(1,ROUNDUP(IFERROR(IF(OR(G35="",G35=0),1,G35),1)*0.1*90/365,0))) -> 1 | J35: =IF(H35<I35,"X","O") -> O | K35: A22 | L35: KNAPP | M35: KNAPP | N35: 10324754_03 | W35: =_xlfn.XLOOKUP(N35,#REF!,#REF!,"없음") -> #REF! | Y35: =_xlfn.XLOOKUP(N35,#REF!,#REF!,"없음") -> #REF!
A36: Conveyor | B36: KNAPP Conveyor | C36: Gear motor | D36: SEW 0.55kw/14.33 | E36: WA30DRN80MK4 50.8265610608.0001.23 | F36: TK01, TK03, WA02, WE01 | G36: 39 | H36: 2 | I36: 2 | J36: =IF(H36<I36,"X","O") -> O | K36: B12 | M36: SEW | N36: 10671423 | W36: =_xlfn.XLOOKUP(N36,#REF!,#REF!,"없음") -> #REF! | Y36: =_xlfn.XLOOKUP(N36,#REF!,#REF!,"없음") -> #REF!
A37: Conveyor | B37: KNAPP Conveyor | C37: Gear motor | D37: SEW 0.75kw/8.2 | E37: WA30DRN80M4 50.8265610603.0001.23 | F37: MK01, TK02, TK03, WA01, WA02, WE02 | G37: 22 | H37: 4 | I37: 3 | J37: =IF(H37<I37,"X","O") -> O | K37: B12 | M37: SEW | N37: 10690980 | W37: =_xlfn.XLOOKUP(N37,#REF!,#REF!,"없음") -> #REF! | X37: 5 | Y37: =_xlfn.XLOOKUP(N37,#REF!,#REF!,"없음") -> #REF! | Z37: KNAPP 2차 SPARE PARTS 추가 입고됨
A38: Conveyor | B38: KNAPP Conveyor | C38: Gear motor | D38: SEW 0.75kw/10.25 | E38: WA30DRN80M4 50.8265610604.0001.23 | F38: MK01, TK01, TK03, WA02, WA03, WE02, ZENB | G38: 19 | H38: 3 | I38: 2 | J38: =IF(H38<I38,"X","O") -> O | K38: B12 | M38: SEW | N38: 10690919 | W38: =_xlfn.XLOOKUP(N38,#REF!,#REF!,"없음") -> #REF! | Y38: =_xlfn.XLOOKUP(N38,#REF!,#REF!,"없음") -> #REF!
A39: Conveyor | B39: KNAPP Conveyor | C39: Gear motor | D39: SEW 0.55kw/8.2 | E39: WA30DRN80MK4 50.8265610609.0001.23 | F39: MK01, TK01, TK03, WA02. WA03, WE01, WE02, ZENB | G39: 19 | H39: 3 | I39: 2 | J39: =IF(H39<I39,"X","O") -> O | K39: B12 | M39: SEW | N39: 10671421 | W39: =_xlfn.XLOOKUP(N39,#REF!,#REF!,"없음") -> #REF! | Y39: =_xlfn.XLOOKUP(N39,#REF!,#REF!,"없음") -> #REF!
A40: Conveyor | B40: KNAPP Conveyor | C40: Gear motor | D40: SEW 0.55kw/10.25 | E40: WA30DRN80MK4 50.8272419803.0001.23 | F40: MK01, TK02, WA02, WA03, WE01 | G40: 10 | H40: 2 | I40: 2 | J40: =IF(H40<I40,"X","O") -> O | K40: B12 | M40: SEW | N40: 10671424 | W40: =_xlfn.XLOOKUP(N40,#REF!,#REF!,"없음") -> #REF! | Y40: =_xlfn.XLOOKUP(N40,#REF!,#REF!,"없음") -> #REF!
A41: Conveyor | B41: KNAPP Conveyor | C41: Gear motor | D41: SEW 0.37kw/8.2 | E41: WA20DRN71M4 50.8274211611.0001.23 | F41: WA03, WE01, WE02 | G41: 8 | H41: 1 | I41: 1 | J41: =IF(H41<I41,"X","O") -> O | K41: B12 | M41: SEW | N41: 10671422 | W41: =_xlfn.XLOOKUP(N41,#REF!,#REF!,"없음") -> #REF! | Y41: =_xlfn.XLOOKUP(N41,#REF!,#REF!,"없음") -> #REF!
A42: Conveyor | B42: KNAPP Conveyor | C42: Gear motor | D42: SEW 0.37kw/10.25 | E42: WA20DRN7M4 50.8468732601.0001.24 | G42: 2 | H42: 2 | I42: =MIN(10,MAX(1,ROUNDUP(IFERROR(IF(OR(G42="",G42=0),1,G42),1)*0.1*90/365,0))) -> 1 | J42: =IF(H42<I42,"X","O") -> O | K42: B12 | M42: SEW | N42: 10671420 | W42: =_xlfn.XLOOKUP(N42,#REF!,#REF!,"없음") -> #REF! | X42: 2 | Y42: =_xlfn.XLOOKUP(N42,#REF!,#REF!,"없음") -> #REF!
A43: Conveyor | B43: KNAPP Conveyor | C43: Gear motor | D43: SEW 0.75kw/6.57 | E43: WA30DRN80M4 50.8265610611.0001.23 | F43: WE01, ZENB | G43: 3 | H43: 2 | I43: =MIN(10,MAX(1,ROUNDUP(IFERROR(IF(OR(G43="",G43=0),1,G43),1)*0.1*90/365,0))) -> 1 | J43: =IF(H43<I43,"X","O") -> O | K43: B12 | M43: SEW | N43: 10490865 | W43: =_xlfn.XLOOKUP(N43,#REF!,#REF!,"없음") -> #REF! | Y43: =_xlfn.XLOOKUP(N43,#REF!,#REF!,"없음") -> #REF!
A44: Conveyor | B44: KNAPP Conveyor | C44: Gear motor | D44: SEW 0.37kw/10.25 | E44: WA20DRN71MS2 50.8265610606.0001.23 | F44: WE01 | G44: 3 | H44: 1 | I44: 2 | J44: =IF(H44<I44,"X","O") -> X | K44: B12 | M44: SEW | N44: 10672265 | W44: =_xlfn.XLOOKUP(N44,#REF!,#REF!,"없음") -> #REF! | Y44: =_xlfn.XLOOKUP(N44,#REF!,#REF!,"없음") -> #REF!
A45: Conveyor | B45: KNAPP Conveyor | C45: Gear motor | D45: SEW 1.5kw/8.64 | E45: SA47DRN90L4 50.546875709.0001.24 | G45: 2 | H45: 1 | I45: =MIN(10,MAX(1,ROUNDUP(IFERROR(IF(OR(G45="",G45=0),1,G45),1)*0.1*90/365,0))) -> 1 | J45: =IF(H45<I45,"X","O") -> O | K45: B22 | M45: SEW | N45: 10686243 | W45: =_xlfn.XLOOKUP(N45,#REF!,#REF!,"없음") -> #REF! | Y45: =_xlfn.XLOOKUP(N45,#REF!,#REF!,"없음") -> #REF!
A46: Conveyor | B46: KNAPP Conveyor | C46: Gear motor | D46: SEW 1.1kw/5.39 | E46: SA47DRN90S4 50.8267513202.0001.23 | F46: WE01 | G46: 1 | H46: 2 | I46: =MIN(10,MAX(1,ROUNDUP(IFERROR(IF(OR(G46="",G46=0),1,G46),1)*0.1*90/365,0))) -> 1 | J46: =IF(H46<I46,"X","O") -> O | K46: B22 | M46: SEW | N46: 10490868 | W46: =_xlfn.XLOOKUP(N46,#REF!,#REF!,"없음") -> #REF! | Y46: =_xlfn.XLOOKUP(N46,#REF!,#REF!,"없음") -> #REF!
A47: Conveyor | B47: KNAPP Conveyor | C47: Gear motor | D47: SEW 1.5kw/14.24 | E47: SA47DRN90LA4 50.8468875704.0001.24 | G47: 1 | H47: 1 | I47: =MIN(10,MAX(1,ROUNDUP(IFERROR(IF(OR(G47="",G47=0),1,G47),1)*0.1*90/365,0))) -> 1 | J47: =IF(H47<I47,"X","O") -> O | K47: B22 | M47: SEW | N47: 10690983 | W47: =_xlfn.XLOOKUP(N47,#REF!,#REF!,"없음") -> #REF! | X47: 2 | Y47: =_xlfn.XLOOKUP(N47,#REF!,#REF!,"없음") -> #REF!
A48: Conveyor | B48: KNAPP Conveyor | C48: Gear motor | D48: SEW 1.1kw/6.83 | E48: SA47DRN90S4 50.8468875715.0001.24 | G48: 1 | H48: 2 | I48: =MIN(10,MAX(1,ROUNDUP(IFERROR(IF(OR(G48="",G48=0),1,G48),1)*0.1*90/365,0))) -> 1 | J48: =IF(H48<I48,"X","O") -> O | K48: B22 | M48: SEW | N48: 10490867 | W48: =_xlfn.XLOOKUP(N48,#REF!,#REF!,"없음") -> #REF! | X48: 2 | Y48: =_xlfn.XLOOKUP(N48,#REF!,#REF!,"없음") -> #REF!
A49: Conveyor | B49: KNAPP Conveyor | C49: Gear motor | D49: SEW 1.1kw/14.24 | E49: SA47DRN90S4 50.8468875703.0001.24 | G49: 5 | H49: 1 | I49: 2 | J49: =IF(H49<I49,"X","O") -> X | K49: B22 | M49: SEW | N49: 10691691 | P49: 1599000 | R49: 1 | W49: =_xlfn.XLOOKUP(N49,#REF!,#REF!,"없음") -> #REF! | X49: 2 | Y49: =_xlfn.XLOOKUP(N49,#REF!,#REF!,"없음") -> #REF!
A50: Conveyor | B50: KNAPP Conveyor | C50: Drive shaft | D50: DRIVE SHAFT AT SEW 0.55 -M, STR_GU | F50: WA02, WE01 | G50: 7 | H50: 2 | I50: =MIN(10,MAX(1,ROUNDUP(IFERROR(IF(OR(G50="",G50=0),1,G50),1)*0.1*90/365,0))) -> 1 | J50: =IF(H50<I50,"X","O") -> O | K50: B21 | M50: SEW | N50: 10327566_02 | W50: =_xlfn.XLOOKUP(N50,#REF!,#REF!,"없음") -> #REF! | X50: 2 | Y50: =_xlfn.XLOOKUP(N50,#REF!,#REF!,"없음") -> #REF!
A51: Conveyor | B51: KNAPP Conveyor | C51: RIBBED V-BELT | D51: 3PJ 376MM CONVEYX. | E51: 376 | G51: 12 | H51: 6 | I51: =MIN(10,MAX(1,ROUNDUP(IFERROR(IF(OR(G51="",G51=0),1,G51),1)*0.1*90/365,0))) -> 1 | J51: =IF(H51<I51,"X","O") -> O | K51: C14 | M51: KNAPP | N51: 10196391 | W51: =_xlfn.XLOOKUP(N51,#REF!,#REF!,"없음") -> #REF! | X51: 6 | Y51: =_xlfn.XLOOKUP(N51,#REF!,#REF!,"없음") -> #REF!
A52: Conveyor | B52: KNAPP Conveyor | C52: RIBBED V-BELT | D52: 2PJ 376MM CONVEYX. | E52: 376 | G52: 21 | H52: 6 | I52: =MIN(10,MAX(1,ROUNDUP(IFERROR(IF(OR(G52="",G52=0),1,G52),1)*0.1*90/365,0))) -> 1 | J52: =IF(H52<I52,"X","O") -> O | K52: C14 | M52: KNAPP | N52: 10201890 | W52: =_xlfn.XLOOKUP(N52,#REF!,#REF!,"없음") -> #REF! | X52: 6 | Y52: =_xlfn.XLOOKUP(N52,#REF!,#REF!,"없음") -> #REF!
A53: Conveyor | B53: KNAPP Conveyor | C53: RIBBED V-BELT | D53: 2PJ 276MM CONVEYX. | E53: 276 | F53: MK01, TK01, TK02, TK03, WA01, WA02, WA03, WE01, WE02 | G53: 55 | H53: 25 | I53: 10 | J53: =IF(H53<I53,"X","O") -> O | K53: C14 | M53: KNAPP | N53: 10709985 | W53: =_xlfn.XLOOKUP(N53,#REF!,#REF!,"없음") -> #REF! | X53: 25 | Y53: =_xlfn.XLOOKUP(N53,#REF!,#REF!,"없음") -> #REF!
A54: Conveyor | B54: KNAPP Conveyor | C54: RIBBED V-BELT | D54: 2PJ 256MM CONVEYX. | E54: 256 | F54: MK01, TK01, TK02, TK03, WA01, WA02, WA03, WE01, WE02, ZENB | G54: 8620 | H54: 220 | I54: =MIN(10,MAX(1,ROUNDUP(IFERROR(IF(OR(G54="",G54=0),1,G54),1)*0.1*90/365,0))) -> 10 | J54: =IF(H54<I54,"X","O") -> O | K54: C14 | M54: KNAPP | N54: 10201326 | W54: =_xlfn.XLOOKUP(N54,#REF!,#REF!,"없음") -> #REF! | X54: 220 | Y54: =_xlfn.XLOOKUP(N54,#REF!,#REF!,"없음") -> #REF!
A55: Conveyor | B55: KNAPP Conveyor | C55: RIBBED V-BELT | D55: 2PJ 314MM CONVEYX. | E55: 314 | F55: MK01, TK01, TK02, TK03, WA01, WA02, WA03, WE01, WE02, ZENB | G55: 92 | H55: 10 | I55: 10 | J55: =IF(H55<I55,"X","O") -> O | K55: C14 | M55: KNAPP | N55: 10201634 | W55: =_xlfn.XLOOKUP(N55,#REF!,#REF!,"없음") -> #REF! | X55: 10 | Y55: =_xlfn.XLOOKUP(N55,#REF!,#REF!,"없음") -> #REF!
A56: Conveyor | B56: KNAPP Conveyor | C56: RIBBED V-BELT | D56: 3PJ 276MM CONVEYX. | E56: 276 | F56: MK01, TK01, TK02, TK03, WA01, WA02, WA03, WE01, WE02 | G56: 74 | H56: 20 | I56: 10 | J56: =IF(H56<I56,"X","O") -> O | K56: C14 | M56: KNAPP | N56: 10709988 | W56: =_xlfn.XLOOKUP(N56,#REF!,#REF!,"없음") -> #REF! | X56: 20 | Y56: =_xlfn.XLOOKUP(N56,#REF!,#REF!,"없음") -> #REF!
A57: Conveyor | B57: KNAPP Conveyor | C57: RIBBED V-BELT | D57: 3PJ 256MM CONVEYX. | E57: 256 | F57: MK01, TK01, TK02, TK03, WA01, WA02, WA03, WE01, WE02, ZENB | G57: 516 | H57: 80 | I57: =MIN(10,MAX(1,ROUNDUP(IFERROR(IF(OR(G57="",G57=0),1,G57),1)*0.1*90/365,0))) -> 10 | J57: =IF(H57<I57,"X","O") -> O | K57: C14 | M57: KNAPP | N57: 10201895 | W57: =_xlfn.XLOOKUP(N57,#REF!,#REF!,"없음") -> #REF! | X57: 80 | Y57: =_xlfn.XLOOKUP(N57,#REF!,#REF!,"없음") -> #REF!
A58: Conveyor | B58: KNAPP Conveyor | C58: RIBBED V-BELT | D58: 3PJ 246MM CONVEYX. | E58: 246 | F58: MK01, TK01, TK02, TK03, WA01, WA02, WA03, WE01, WE02, ZENB | G58: 481 | H58: 140 | I58: =MIN(10,MAX(1,ROUNDUP(IFERROR(IF(OR(G58="",G58=0),1,G58),1)*0.1*90/365,0))) -> 10 | J58: =IF(H58<I58,"X","O") -> O | K58: C14 | M58: KNAPP | N58: 10196325 | W58: =_xlfn.XLOOKUP(N58,#REF!,#REF!,"없음") -> #REF! | Y58: =_xlfn.XLOOKUP(N58,#REF!,#REF!,"없음") -> #REF!
A59: Conveyor | B59: KNAPP Conveyor | C59: RIBBED V-BELT | D59: 2PJ 246MM CONVEYX. | E59: 246 | F59: MK01, TK01, TK02, TK03, WA01, WA02, WA03, WE01, WE02, ZENB | G59: 1827 | H59: 80 | I59: =MIN(10,MAX(1,ROUNDUP(IFERROR(IF(OR(G59="",G59=0),1,G59),1)*0.1*90/365,0))) -> 10 | J59: =IF(H59<I59,"X","O") -> O | K59: C14 | M59: KNAPP | N59: 10201894 | W59: =_xlfn.XLOOKUP(N59,#REF!,#REF!,"없음") -> #REF! | X59: 80 | Y59: =_xlfn.XLOOKUP(N59,#REF!,#REF!,"없음") -> #REF!
A60: Conveyor | B60: KNAPP Conveyor | C60: RIBBED V-BELT | D60: 2PJ 284MM CONVEYX. | E60: 284 | F60: MK01, SH01, SH02, TK01, TK03, WA02, WE01, WE02, ZENB | G60: 2233 | H60: 120 | I60: =MIN(10,MAX(1,ROUNDUP(IFERROR(IF(OR(G60="",G60=0),1,G60),1)*0.1*90/365,0))) -> 10 | J60: =IF(H60<I60,"X","O") -> O | K60: C14 | M60: KNAPP | N60: 10201500 | W60: =_xlfn.XLOOKUP(N60,#REF!,#REF!,"없음") -> #REF! | X60: 120 | Y60: =_xlfn.XLOOKUP(N60,#REF!,#REF!,"없음") -> #REF!
A61: Conveyor | B61: KNAPP Conveyor | C61: RIBBED V-BELT | D61: 2PJ 336MM CONVEYX. | E61: 336 | F61: WA02, WA03, WE01, WE02 | G61: 22 | H61: 15 | I61: 10 | J61: =IF(H61<I61,"X","O") -> O | K61: C14 | M61: KNAPP | N61: 10201577 | W61: =_xlfn.XLOOKUP(N61,#REF!,#REF!,"없음") -> #REF! | X61: 15 | Y61: =_xlfn.XLOOKUP(N61,#REF!,#REF!,"없음") -> #REF!
A62: Conveyor | B62: KNAPP Conveyor | C62: RIBBED V-BELT | D62: 3PJ 314MM CONVEYX. | E62: 314 | F62: WA02, WA03, WE01, WE02 | G62: 11 | H62: 12 | I62: 10 | J62: =IF(H62<I62,"X","O") -> O | K62: C14 | M62: KNAPP | N62: 10196439 | W62: =_xlfn.XLOOKUP(N62,#REF!,#REF!,"없음") -> #REF! | X62: 12 | Y62: =_xlfn.XLOOKUP(N62,#REF!,#REF!,"없음") -> #REF!
A63: Conveyor | B63: KNAPP Conveyor | C63: RIBBED V-BELT | D63: 6PJ 456MM CONVEYX. | E63: 456 | F63: WE01 | G63: 4 | H63: 1 | I63: 10 | J63: =IF(H63<I63,"X","O") -> X | K63: C14 | M63: KNAPP | N63: 10196563 | W63: =_xlfn.XLOOKUP(N63,#REF!,#REF!,"없음") -> #REF! | Y63: =_xlfn.XLOOKUP(N63,#REF!,#REF!,"없음") -> #REF!
A64: Conveyor | B64: KNAPP Conveyor | C64: FREQUENCY CONVERTER | D64: G115D FSA 1,10KW... | F64: MK01, TK02, WA03, WE01, WE02, ZENB | G64: 10 | H64: 3 | I64: 2 | J64: =IF(H64<I64,"X","O") -> O | K64: 212 | N64: 10676615 | W64: =_xlfn.XLOOKUP(N64,#REF!,#REF!,"없음") -> #REF! | X64: 3 | Y64: =_xlfn.XLOOKUP(N64,#REF!,#REF!,"없음") -> #REF!
A65: Conveyor | B65: KNAPP Conveyor | C65: FREQUENCY CONVERTER | D65: G115D FSA 0,75KW... | F65: TK02, WA02, WE01, WE02, ZENB | G65: 8 | H65: 2 | I65: 2 | J65: =IF(H65<I65,"X","O") -> O | K65: 232 | N65: 10676614 | W65: =_xlfn.XLOOKUP(N65,#REF!,#REF!,"없음") -> #REF! | Y65: =_xlfn.XLOOKUP(N65,#REF!,#REF!,"없음") -> #REF!
A66: Conveyor | B66: KNAPP Conveyor | C66: FREQUENCY CONVERTER | D66: G115D FSA 0,37KW... | F66: WE01, ZENB | G66: 7 | H66: 2 | I66: 2 | J66: =IF(H66<I66,"X","O") -> O | K66: 212 | N66: 10676612 | W66: =_xlfn.XLOOKUP(N66,#REF!,#REF!,"없음") -> #REF! | Y66: =_xlfn.XLOOKUP(N66,#REF!,#REF!,"없음") -> #REF!
A67: Conveyor | B67: KNAPP Conveyor | C67: SOLENOID VALVE | D67: SMC 3kw/2 V111-5G-X449 M8 | F67: #REF! | G67: 0 | H67: 28 | I67: 2 | J67: =IF(H67<I67,"X","O") -> O | K67: 203 | N67: 10196883 | W67: =_xlfn.XLOOKUP(N67,#REF!,#REF!,"없음") -> #REF! | X67: 12 | Y67: =_xlfn.XLOOKUP(N67,#REF!,#REF!,"없음") -> #REF!
A68: Conveyor | B68: KNAPP Conveyor | C68: SOLENOID VALVE | D68: SOLENOID VALVE, VUVG-L14-M52-MT-G18-1R8L | F68: TK01, TK03, WA02, WA03, WE01, WE02, ZENB | G68: 88 | H68: 8 | I68: 2 | J68: =IF(H68<I68,"X","O") -> O | K68: 321 | N68: 10195348 | W68: =_xlfn.XLOOKUP(N68,#REF!,#REF!,"없음") -> #REF! | Y68: =_xlfn.XLOOKUP(N68,#REF!,#REF!,"없음") -> #REF!
A69: Conveyor | B69: KNAPP Conveyor | C69: Motor Module | D69: Ikw/O MODULE, ASI VBA-3E3A-G20-ZELkw/E2L-… | E69: 3in 3out | F69: MK01, SH01, ZORS, ZENB, SH02, TK01, TK02, TK03, WA01, WA02, WA03, WE01, WE01 | G69: 1012 | H69: 9 | I69: 2 | J69: =IF(H69<I69,"X","O") -> O | K69: 223 | M69: KNAPP | N69: 10662772_01 | W69: =_xlfn.XLOOKUP(N69,#REF!,#REF!,"없음") -> #REF! | Y69: =_xlfn.XLOOKUP(N69,#REF!,#REF!,"없음") -> #REF!
A70: Conveyor | B70: KNAPP Conveyor | C70: Motor Module | D70: MOTOR MODULE, ASI VBA-4E3A-G20-ZELkw/M1.. | E70: 2in 2out | F70: MK01, SH01, SH02, TK01, TK02, TK03, WA01, WA02, WA03, WE01, WE02, ZENB, ZOSR | G70: 1412 | H70: 8 | I70: 2 | J70: =IF(H70<I70,"X","O") -> O | K70: 223 | M70: KNAPP | N70: 10662775_01 | W70: =_xlfn.XLOOKUP(N70,#REF!,#REF!,"없음") -> #REF! | Y70: =_xlfn.XLOOKUP(N70,#REF!,#REF!,"없음") -> #REF!
A71: Conveyor | B71: KNAPP Conveyor | C71: OPTICAL SENSOR | D71: GL6-P0511S80 10-30V PNP | F71: MK01, TK01, TK02, TK03, WA01, WA02, WA03, WE01, WE02 | G71: 334 | H71: 9 | I71: 3 | J71: =IF(H71<I71,"X","O") -> O | K71: 213 | M71: SICK | N71: 10452176 | W71: =_xlfn.XLOOKUP(N71,#REF!,#REF!,"없음") -> #REF! | Y71: =_xlfn.XLOOKUP(N71,#REF!,#REF!,"없음") -> #REF!
A72: Conveyor | B72: KNAPP Conveyor | C72: Sensor | D72: OPTICAL SENSOR, WTS16P-24161120A00 | E72: Distance check sensor(거리 제어 센서) | F72: MK01, TK02, WA01, WA03, WE02 | G72: 90 | H72: 2 | I72: 1 | J72: =IF(H72<I72,"X","O") -> O | K72: 213 | M72: Sick | N72: 10759834 | O72: 382.36 | W72: =_xlfn.XLOOKUP(N72,#REF!,#REF!,"없음") -> #REF! | X72: 5 | Y72: =_xlfn.XLOOKUP(N72,#REF!,#REF!,"없음") -> #REF!
A73: Conveyor | B73: KNAPP Conveyor | C73: OPTICAL SENSOR | D73: WL9-3P2230 | F73: SH01, SH02, ZOSR | G73: 68 | H73: 6 | I73: 3 | J73: =IF(H73<I73,"X","O") -> O | K73: 213 | N73: 10214637 | W73: =_xlfn.XLOOKUP(N73,#REF!,#REF!,"없음") -> #REF! | X73: 6 | Y73: =_xlfn.XLOOKUP(N73,#REF!,#REF!,"없음") -> #REF!
A74: Conveyor | B74: KNAPP Conveyor | C74: OPTICAL SENSOR | D74: WTB8-P2231 | F74: SH01, SH02 | G74: 16 | H74: 3 | I74: 3 | J74: =IF(H74<I74,"X","O") -> O | K74: 213 | N74: 10524300 | W74: =_xlfn.XLOOKUP(N74,#REF!,#REF!,"없음") -> #REF! | X74: 3 | Y74: =_xlfn.XLOOKUP(N74,#REF!,#REF!,"없음") -> #REF!
A75: Conveyor | B75: KNAPP Conveyor | C75: OPTICAL SENSOR | D75: OPTICAL SENSOR, WTB16I-24161120A00 HGA | G75: 10 | H75: 8 | I75: 2 | J75: =IF(H75<I75,"X","O") -> O | K75: 213 | M75: SICK | N75: 10574742 | W75: =_xlfn.XLOOKUP(N75,#REF!,#REF!,"없음") -> #REF! | Y75: =_xlfn.XLOOKUP(N75,#REF!,#REF!,"없음") -> #REF!
A76: Conveyor | B76: KNAPP Conveyor | C76: OPTICAL SENSOR | D76: P1KL023 REFL.LS | F76: SH01, SH02 | G76: 336 | H76: 7 | I76: 3 | J76: =IF(H76<I76,"X","O") -> O | K76: 213 | N76: 10510473 | W76: =_xlfn.XLOOKUP(N76,#REF!,#REF!,"없음") -> #REF! | X76: 7 | Y76: =_xlfn.XLOOKUP(N76,#REF!,#REF!,"없음") -> #REF!
A77: Conveyor | B77: KNAPP Conveyor | C77: OPTICAL SENSOR | D77: OPT1515 | F77: ZENB | G77: 1 | H77: 1 | I77: 2 | J77: =IF(H77<I77,"X","O") -> X | K77: 213 | M77: Wenglor | N77: 10695050 | W77: =_xlfn.XLOOKUP(N77,#REF!,#REF!,"없음") -> #REF! | Y77: =_xlfn.XLOOKUP(N77,#REF!,#REF!,"없음") -> #REF!
A78: Conveyor | B78: KNAPP VMS | C78: OPTICAL SENSOR | D78: 24106349 Light barrier GL6G-P4211 | F78: WE01 | G78: 2 | H78: 2 | I78: 2 | J78: =IF(H78<I78,"X","O") -> O | K78: 213 | N78: 10244024 | W78: =_xlfn.XLOOKUP(N78,#REF!,#REF!,"없음") -> #REF! | Y78: =_xlfn.XLOOKUP(N78,#REF!,#REF!,"없음") -> #REF!
A79: Conveyor | B79: KNAPP Conveyor | C79: BEARING | D79: BALL BEARING DIN625-1 6000-2RZkw/C3H | G79: 38 | H79: 26 | I79: 2 | J79: =IF(H79<I79,"X","O") -> O | K79: C14 | L79: KNAPP | M79: HCH | N79: 10199351 | O79: 0.74 | W79: =_xlfn.XLOOKUP(N79,#REF!,#REF!,"없음") -> #REF! | X79: 26 | Y79: =_xlfn.XLOOKUP(N79,#REF!,#REF!,"없음") -> #REF!
A80: Conveyor | B80: KNAPP Conveyor | C80: BEARING | D80: BALL BEARING DIN630 2305-2RS-TV | G80: 86 | H80: 8 | I80: 2 | J80: =IF(H80<I80,"X","O") -> O | K80: C14 | L80: KNAPP | N80: 10198923 | O80: 21.02 | W80: =_xlfn.XLOOKUP(N80,#REF!,#REF!,"없음") -> #REF! | X80: 8 | Y80: =_xlfn.XLOOKUP(N80,#REF!,#REF!,"없음") -> #REF!
A81: Conveyor | B81: KNAPP Conveyor | C81: BEARING | D81: BALL BEARING DIN625-1 61810-2RZkw/C3H | G81: 216 | H81: 112 | I81: 2 | J81: =IF(H81<I81,"X","O") -> O | K81: C14 | L81: KNAPP | N81: 10199360 | O81: 2.61 | W81: =_xlfn.XLOOKUP(N81,#REF!,#REF!,"없음") -> #REF! | Y81: =_xlfn.XLOOKUP(N81,#REF!,#REF!,"없음") -> #REF!
A82: Conveyor | B82: KNAPP Conveyor | C82: Roller | D82: Carrier roller Int NB=900 MR M. CLIPS.. | E82: 컨베이어 롤러 NB=900mm (무동력 | H82: 10 | I82: 2 | J82: =IF(H82<I82,"X","O") -> O | N82: 10328173_02_0011 | W82: =_xlfn.XLOOKUP(N82,#REF!,#REF!,"없음") -> #REF! | Y82: =_xlfn.XLOOKUP(N82,#REF!,#REF!,"없음") -> #REF!
A83: Conveyor | B83: KNAPP Conveyor | C83: BEARING | D83: BALL BEARING DIN625-1 6201-2RZkw/C3H | G83: 418 | H83: 10 | I83: 2 | J83: =IF(H83<I83,"X","O") -> O | K83: C14 | N83: 10199348 | O83: 0.85 | W83: =_xlfn.XLOOKUP(N83,#REF!,#REF!,"없음") -> #REF! | Y83: =_xlfn.XLOOKUP(N83,#REF!,#REF!,"없음") -> #REF!
A84: Conveyor | B84: KNAPP Conveyor | C84: Roller | D84: PRESSURE ROLLER, STR_RF TYP1 -M | G84: 18 | H84: 3 | I84: 2 | J84: =IF(H84<I84,"X","O") -> O | K84: B21 | N84: 10196377_01 | O84: 5.69 | W84: =_xlfn.XLOOKUP(N84,#REF!,#REF!,"없음") -> #REF! | Y84: =_xlfn.XLOOKUP(N84,#REF!,#REF!,"없음") -> #REF!
A85: Conveyor | B85: KNAPP Conveyor | C85: Load switch | D85: KH32 T204kw/A M736 VE(32A)4-P | E85: 로드스위치 | G85: 4 | H85: 1 | I85: 1 | J85: =IF(H85<I85,"X","O") -> O | K85: 222 | M85: Kraus & Naimer | N85: 10222387 | O85: 118.93 | T85: 1 | W85: =_xlfn.XLOOKUP(N85,#REF!,#REF!,"없음") -> #REF! | Y85: =_xlfn.XLOOKUP(N85,#REF!,#REF!,"없음") -> #REF!
A86: Conveyor | B86: KNAPP Conveyor | C86: BRAKE ROLLER | D86: ABR -KPL, STR_SRF | G86: 144 | H86: 4 | I86: 4 | J86: =IF(H86<I86,"X","O") -> O | K86: C14 | N86: 10324599_01 | O86: 63.69 | W86: =_xlfn.XLOOKUP(N86,#REF!,#REF!,"없음") -> #REF! | X86: 4 | Y86: =_xlfn.XLOOKUP(N86,#REF!,#REF!,"없음") -> #REF!
A87: Conveyor | B87: KNAPP Conveyor | C87: Roller | D87: PRESSURE ROLLER, STR_RF TYP2 -M | G87: 35 | H87: 2 | I87: 2 | J87: =IF(H87<I87,"X","O") -> O | K87: B21 | N87: 10196379_01 | O87: 5.64 | T87: 1 | W87: =_xlfn.XLOOKUP(N87,#REF!,#REF!,"없음") -> #REF! | Y87: =_xlfn.XLOOKUP(N87,#REF!,#REF!,"없음") -> #REF!
A88: Conveyor | B88: KNAPP Conveyor | C88: =UPPER(_xlfn.TEXTBEFORE(D88, " ", 2)) -> TENSION ROLLER | D88: TENSION ROLLER V2 US -M, STR_GU | G88: 171 | H88: 7 | I88: =_xlfn.CEILING.MATH(_xlfn.NORM.S.INV(IF(S88="A",0.99,IF(S88="B",0.95,IF(S88="C",0.9,0.95))))*SQRT(T88/365)*SQRT(R88*30),1) -> 1 | J88: =IF(H88<I88,"X","O") -> O | K88: C14 | L88: KNAPP | N88: 10615028_01 | O88: 6.24 | R88: 3 | S88: B | T88: 1 | U88: =_xlfn.CEILING.MATH(_xlfn.NORM.S.INV(IF(S88="A",0.99,IF(S88="B",0.95,IF(S88="C",0.9,0.95))))*SQRT((G88*T88)/365)*SQRT(R88*30),1) -> 11 | V88: =H88+U88 -> 18 | W88: =_xlfn.XLOOKUP(N88,#REF!,#REF!,"없음") -> #REF! | Y88: =_xlfn.XLOOKUP(N88,#REF!,#REF!,"없음") -> #REF!
A89: Conveyor | B89: KNAPP Conveyor | C89: WHEEL | D89: WHEEL NB1=660 Int V3 -K, STR_RW | E89: WHEEL | F89: Switch roller, 축 중앙에 Velt 풀리 달려있는 롤러 | G89: 24 | H89: 1 | I89: 2 | J89: =IF(H89<I89,"X","O") -> X | K89: C14 | L89: KNAPP | N89: 10516646_01_0006 | V89: =H89+U89 -> 1 | W89: =_xlfn.XLOOKUP(N89,#REF!,#REF!,"없음") -> #REF! | Y89: =_xlfn.XLOOKUP(N89,#REF!,#REF!,"없음") -> #REF!
A90: ASRS | B90: KNAPP SHUTTLE | C90: Shuttle | D90: Shuttle Typ=3 2D Vario Shuttle V2 -Kp... | E90: Shuttle | F90: OSR Shuttle | G90: 90 | H90: 6 | I90: 6 | J90: =IF(H90<I90,"X","O") -> O | L90: KNAPP | N90: 10689623_01_0011 | O90: 74440.7 | V90: =H90+U90 -> 6 | Z90: KNAPP 2차 SPARE PARTS 새로운 품목
A91: ASRS | B91: KNAPP SHUTTLE | C91: Wheel | D91: SIDE GUIDE WHEEL, COMPENSA EBG, OSR_EVO | E91: 사이드 가이드 휠 | F91: OSR Shuttle | G91: 360 | H91: 100 | I91: 0 | J91: =IF(H91<I91,"X","O") -> O | K91: 242 | L91: KNAPP | N91: 10679338_01 | V91: =H91+U91 -> 100 | W91: =_xlfn.XLOOKUP(N91,#REF!,#REF!,"없음") -> #REF! | X91: 110 | Y91: =_xlfn.XLOOKUP(N91,#REF!,#REF!,"없음") -> #REF!
A92: ASRS | B92: KNAPP SHUTTLE | C92: Wheel | D92: Sideguide wheel_Vibration buffer | E92: 사이드 가이드 휠의 고무 버퍼 | F92: OSR Shuttle | G92: 360 | H92: 70 | I92: 0 | J92: =IF(H92<I92,"X","O") -> O | K92: 242 | L92: KNAPP | N92: 10634710_01 | V92: =H92+U92 -> 70 | W92: =_xlfn.XLOOKUP(N92,#REF!,#REF!,"없음") -> #REF! | Y92: =_xlfn.XLOOKUP(N92,#REF!,#REF!,"없음") -> #REF!
A93: ASRS | B93: KNAPP SHUTTLE | C93: Wheel | D93: Sideguide wheel_Bracket (Front left side, rear right side | E93: 사이드 가이드 휠_브라켓 | F93: OSR Shuttle | G93: 90 | H93: 26 | I93: 0 | J93: =IF(H93<I93,"X","O") -> O | K93: 242 | L93: KNAPP | N93: 10611156_02 | V93: =H93+U93 -> 26 | W93: =_xlfn.XLOOKUP(N93,#REF!,#REF!,"없음") -> #REF! | Y93: =_xlfn.XLOOKUP(N93,#REF!,#REF!,"없음") -> #REF!
A94: ASRS | B94: KNAPP SHUTTLE | C94: Wheel | D94: Sideguide wheel_Bracket (Front right side, Rear left side | E94: 사이드 가이드 휠_브라켓 | F94: OSR Shuttle | G94: 90 | H94: 11 | I94: 0 | J94: =IF(H94<I94,"X","O") -> O | K94: 242 | L94: KNAPP | N94: 10611156_03 | V94: =H94+U94 -> 11 | W94: =_xlfn.XLOOKUP(N94,#REF!,#REF!,"없음") -> #REF! | Y94: =_xlfn.XLOOKUP(N94,#REF!,#REF!,"없음") -> #REF!
A95: ASRS | B95: KNAPP SHUTTLE | C95: Wheel | D95: SIDE GUIDE V8 EBG -M, OSR_EVO (Front left side, Rear right side) | E95: 사이드 가이드 휠 일체형(개선품) | F95: OSR Shuttle | G95: 360 | H95: 94 | I95: =_xlfn.LET( _xlpm.orderNum, N95, _xlpm.usedCount, COUNTIFS('ASRS parts replacement'!F:F, _xlpm.orderNum, 'ASRS parts replacement'!A:A, ">=2025-01-01", 'ASRS parts replacement'!A:A, "<=2025-12-31"), IF(_xlpm.usedCount=0, 2, MAX(2, _xlpm.usedCount/12*6*2)) ) -> 17 | J95: =IF(H95<I95,"X","O") -> O | K95: 242 | L95: KNAPP | N95: 10907771_02 | O95: 45.78 | R95: 2M | V95: =H95+U95 -> 94 | W95: =_xlfn.XLOOKUP(N95,#REF!,#REF!,"없음") -> #REF! | Y95: =_xlfn.XLOOKUP(N95,#REF!,#REF!,"없음") -> #REF!
A96: ASRS | B96: KNAPP SHUTTLE | C96: Wheel | D96: SIDE GUIDE V8 EBG -M, OSR_EVO (Front right side, Rear left side) | E96: 사이드 가이드 휠 일체형(개선품) | F96: OSR Shuttle | G96: 360 | H96: 93 | I96: =_xlfn.LET( _xlpm.orderNum, N96, _xlpm.usedCount, COUNTIFS('ASRS parts replacement'!F:F, _xlpm.orderNum, 'ASRS parts replacement'!A:A, ">=2025-01-01", 'ASRS parts replacement'!A:A, "<=2025-12-31"), IF(_xlpm.usedCount=0, 2, MAX(2, _xlpm.usedCount/12*6*2)) ) -> 18 | J96: =IF(H96<I96,"X","O") -> O | K96: 242 | L96: KNAPP | N96: 10907771_03 | O96: 45.78 | R96: 2M | V96: =H96+U96 -> 93 | W96: =_xlfn.XLOOKUP(N96,#REF!,#REF!,"없음") -> #REF! | Y96: =_xlfn.XLOOKUP(N96,#REF!,#REF!,"없음") -> #REF!
A97: ASRS | B97: KNAPP SHUTTLE | C97: Wheel | D97: BOGIE WHEEL, LFW ABLF EBG OSR_EVO | E97: 종방향 주행 휠 | F97: OSR Shuttle | G97: 360 | H97: 61 | I97: =_xlfn.LET( _xlpm.orderNum, N97, _xlpm.usedCount, COUNTIFS('ASRS parts replacement'!F:F, _xlpm.orderNum, 'ASRS parts replacement'!A:A, ">=2025-01-01", 'ASRS parts replacement'!A:A, "<=2025-12-31"), IF(_xlpm.usedCount=0, 2, MAX(2, _xlpm.usedCount/12*6*2)) ) -> 7 | J97: =IF(H97<I97,"X","O") -> O | K97: 242 | L97: KNAPP | N97: 10567315_01 | O97: 64.6 | P97: =O97*1680 -> 108528 | R97: 2M | V97: =H97+U97 -> 61 | W97: =_xlfn.XLOOKUP(N97,#REF!,#REF!,"없음") -> #REF! | Y97: =_xlfn.XLOOKUP(N97,#REF!,#REF!,"없음") -> #REF!
A98: ASRS | B98: KNAPP SHUTTLE | C98: Wheel | D98: BOGIE WHEEL, QFW ABLF EBG, OSR_EVO | E98: 횡방향 주행 휠 | F98: OSR Shuttle | G98: 360 | H98: 146 | I98: =_xlfn.LET( _xlpm.orderNum, N98, _xlpm.usedCount, COUNTIFS('ASRS parts replacement'!F:F, _xlpm.orderNum, 'ASRS parts replacement'!A:A, ">=2025-01-01", 'ASRS parts replacement'!A:A, "<=2025-12-31"), IF(_xlpm.usedCount=0, 2, MAX(2, _xlpm.usedCount/12*6*2)) ) -> 17 | J98: =IF(H98<I98,"X","O") -> O | K98: 242 | L98: KNAPP | N98: 10567316_01 | O98: 53.39 | P98: =O98*1680 -> 89695.2 | R98: 2M | V98: =H98+U98 -> 146 | W98: =_xlfn.XLOOKUP(N98,#REF!,#REF!,"없음") -> #REF! | X98: 98 | Y98: =_xlfn.XLOOKUP(N98,#REF!,#REF!,"없음") -> #REF!
A99: ASRS | B99: KNAPP SHUTTLE | C99: Current Collector | D99: CURRENT COLLECTOR, 0815 2P1PH 35A REV... | E99: 커런트 컬렉터 | F99: OSR Shuttle | G99: 180 | H99: 104 | I99: =_xlfn.LET( _xlpm.orderNum, N99, _xlpm.usedCount, COUNTIFS('ASRS parts replacement'!F:F, _xlpm.orderNum, 'ASRS parts replacement'!A:A, ">=2025-01-01", 'ASRS parts replacement'!A:A, "<=2025-12-31"), IF(_xlpm.usedCount=0, 2, MAX(2, _xlpm.usedCount/12*6*2)) ) -> 47 | J99: =IF(H99<I99,"X","O") -> O | K99: 202 | L99: KNAPP | N99: 10764610_01 | O99: 170.83 | P99: =O99*1680 -> 286994.4 | R99: 2M | V99: =H99+U99 -> 104 | W99: =_xlfn.XLOOKUP(N99,#REF!,#REF!,"없음") -> #REF! | X99: 28 | Y99: =_xlfn.XLOOKUP(N99,#REF!,#REF!,"없음") -> #REF!
A100: ASRS | B100: KNAPP SHUTTLE | C100: Current Collector | D100: CURRENT COLLECTOR PAIR 1 Set | E100: 커런트 컬렉터 (1 Set 기준) | F100: OSR Shuttle | G100: 180 | H100: 378 | I100: =_xlfn.LET( _xlpm.orderNum, N100, _xlpm.usedCount, COUNTIFS('ASRS parts replacement'!F:F, _xlpm.orderNum, 'ASRS parts replacement'!A:A, ">=2025-01-01", 'ASRS parts replacement'!A:A, "<=2025-12-31"), IF(_xlpm.usedCount=0, 2, MAX(2, _xlpm.usedCount/12*6*2)) ) -> 150 | J100: =IF(H100<I100,"X","O") -> O | K100: 202 | L100: 인원엔지니어링 | N100: 1 | O100: 90,000 원 | P100: =O100*1680 -> #VALUE! | R100: 3M | V100: =H100+U100 -> 378 | W100: =_xlfn.XLOOKUP(N100,#REF!,#REF!,"없음") -> #REF! | Y100: =_xlfn.XLOOKUP(N100,#REF!,#REF!,"없음") -> #REF!
...

Sheet Parts purchase
A1: Order type | B1: Owner | C1: Order & Request date | D1: Vendor | E1: Order NO. | F1: Description | G1: 한글 설명 | H1: 주문 수량 | I1: UNIT | J1: 입고일
A2: NIKE ORDER | C2: 45211 | D2: DLS | E2: 10411034_01 | F2: GEAR MOTOR ELR 220/10/3500 48V BL70S-... | G2: 크로스 주행 모터 | H2: 6 | I2: PC | J2: 45254
A3: NIKE ORDER | C3: 45211 | D3: DLS | E3: 10411039_01 | F3: LIFT DRIVE UNIT E60H4+EMT245 ELR 48VDC | G3: LIFT DRIVE UNIT E60H4+EMT245 ELR 48VDC | H3: 6 | I3: PC | J3: 45254
A4: NIKE ORDER | C4: 45211 | D4: DLS | E4: 10764610_01 | F4: CURRENT COLLECTOR, 0815 2P1PH 35A REV... | G4: 커런트 컬렉터 | H4: 30 | I4: PC | J4: 45254
A5: NIKE ORDER | C5: 45211 | D5: DLS | E5: 10567315_01 | F5: BOGIE WHEEL, LFW ABLF EBG OSR_EVO | G5: 메인 통로 주행 휠 | H5: 20 | I5: PC | J5: 45254
A6: NIKE ORDER | C6: 45211 | D6: DLS | E6: 10567316_01 | F6: BOGIE WHEEL, QFW ABLF EBG, OSR_EVO | G6: 크로스 통로 주행 휠 | H6: 20 | I6: PC | J6: 45254
A7: NIKE ORDER | C7: 45212 | D7: DLS | E7: 10412613_02 | F7: CORNER ELEMENT EBG -M, OSR_EVO | G7: Corner element (Corner cover)_Front left side | H7: 2 | I7: PC | J7: 45274
A8: NIKE ORDER | C8: 45212 | D8: DLS | E8: 10412613_04 | F8: CORNER ELEMENT EBG -M, OSR_EVO | G8: Corner element (Corner cover)_Front right side | H8: 2 | I8: PC | J8: 45274
A9: NIKE ORDER | C9: 45212 | D9: DLS | E9: 10412613_03 | F9: CORNER ELEMENT EBG -M, OSR_EVO | G9: Corner element (Corner cover)_Rear left side | H9: 3 | I9: PC | J9: 45274
A10: NIKE ORDER | C10: 45212 | D10: DLS | E10: 10412613_05 | F10: CORNER ELEMENT EBG -M, OSR_EVO | G10: Corner element (Corner cover)_Rear right side | H10: 2 | I10: PC | J10: 45274
A11: NIKE ORDER | C11: 45212 | D11: DLS | E11: 10410230_01 | F11: GEAR MOTOR ELR 350/7.5/3150 24V BL70M... | G11: 메인 주행 휠 모터 | H11: 3 | I11: PC | J11: 45274
A12: NIKE ORDER | C12: 45212 | D12: DLS | E12: 10395200_01 | F12: GEAR MOTOR ELR/11.8 48V BL57AL-48V + ... | G12: 텔레스코프 모터 | H12: 3 | I12: PC | J12: 45274
A13: NIKE ORDER | C13: 45212 | D13: DLS | E13: 10540023_01 | F13: GEAR MOTOR ELR/33/3000 48V BL42YS-48V... | G13: 바리오 센터링 모터 | H13: 3 | I13: PC | J13: 45274
... A16: NIKE ORDER | C16: 45212 | D16: DLS | E16: 10652991_01 | F16: TABLET, KAG ZEBRA ET51 10" RW INKL. R... | G16: SCADA 테블릿 | H16: 2 | I16: PC | J16: 45274
A17: Warranty | D17: DLS | E17: 10412613_02 | F17: CORNER ELEMENT EBG -M, OSR_EVO | G17: Corner element (Corner cover)_Front left side | H17: 3 | I17: PC | J17: 45230
A18: Warranty | D18: DLS | E18: 10412613_04 | F18: CORNER ELEMENT EBG -M, OSR_EVO | G18: Corner element (Corner cover)_Front right side | H18: 3 | I18: PC | J18: 45230
A19: Warranty | D19: DLS | E19: 10412613_03 | F19: CORNER ELEMENT EBG -M, OSR_EVO | G19: Corner element (Corner cover)_Rear left side | H19: 3 | I19: PC | J19: 45230
A20: Warranty | D20: DLS | E20: 10412613_05 | F20: CORNER ELEMENT EBG -M, OSR_EVO | G20: Corner element (Corner cover)_Rear right side | H20: 3 | I20: PC | J20: 45230
A21: Warranty | D21: DLS | E21: 10849086_01 | F21: SCANNER, Cognex, DM280 | G21: 바코드 스캐너 | H21: 1 | I21: PC | J21: 45230
A22: Warranty | D22: DLS | E22: 10764610_01 | F22: CURRENT COLLECTOR, 0815 2P1PH 35A REV... | H22: 20 | I22: PC | J22: 45216
A23: Warranty | D23: DLS | E23: 10764610_01 | F23: CURRENT COLLECTOR, 0815 2P1PH 35A REV... | H23: 72 | I23: PC | J23: 45230
A24: Warranty | D24: DLS | E24: 10411039_01 | F24: LIFT DRIVE UNIT E60H4+EMT245 ELR 48VDC | G24: LIFT DRIVE UNIT E60H4+EMT245 ELR 48VDC / MOTOR2 | H24: 5 | I24: PC | J24: 45268
A25: NIKE ORDER | C25: 발주완료 | D25: 엘림철물 | E25: Unknown | F25: PILZ Safety switch 506334 (506301+506308) | G25: 랙 통로 Door safety switch | H25: 2 | I25: PC | J25: 45293
A26: Warranty | C26: 45243 | D26: DLS | E26: 10609544_02_0001 | F26: ACCESS CONCEPT LZYL=4510 LINKS 1E V2 ... | G26: KNAPP LOCK 장치 | H26: 3 | I26: PC | J26: 45351
A27: Warranty | C27: 45243 | D27: DLS | E27: 10709974_01 | F27: ACCESS POINT, KAG ARUBA AP-504 RW CON… | G27: Network AP | H27: 1 | I27: PC | J27: 45280
A28: Warranty | C28: 45243 | D28: DLS | E28: 10679338_01 | F28: SIDE GUIDE WHEEL COMPENSA EBG -M, OSR… | H28: 4 | I28: PC
A29: Warranty | C29: 45194 | D29: DLS | E29: 10411034_01 | F29: GEAR MOTOR ELR 220/10/3500 48V BL70S-... | G29: 크로스 주행 모터 (모터2) | H29: 10 | I29: PC | J29: 45268
A30: Warranty | D30: DLS | E30: 10416079_01 | F30: CURRENT COLLECTOR, 0815 2P1PH 35A REV... | H30: 12 | I30: PC | J30: 45268
A31: Warranty | D31: DLS | E31: 10328021_02_0017 | F31: Motorized roller NB=900 Int MR -M, ST | G31: 컨베이어 롤러 NB=900mm | H31: 10 | I31: PC | J31: 45268
A32: Warranty | D32: DLS | E32: 10328173_02_0011 | F32: Carrier roller Int NB=900 MR M. CLIPS.. | H32: 10 | I32: PC | J32: 45268
A33: Warranty | C33: 45194 | D33: DLS | E33: 10540023_01 | F33: GEAR MOTOR ELR/33/3000 48V BL42YS-48V... | G33: 바리오 센터링 모터 | H33: 1 | I33: PC
A34: Warranty | C34: 45194 | D34: DLS | E34: 10411039_01 | F34: LIFT DRIVE UNIT E60H4+EMT245 ELR 48VDC | G34: LIFT DRIVE UNIT E60H4+EMT245 ELR 48VDC | H34: 3 | I34: PC
A35: Warranty | C35: 45194 | D35: DLS | E35: 10519144 | F35: INDUCTIVE SENSOR, SICK IMA18-20NE1ZC0K | G35: 셔틀 하부 크로스 레일 감지 | H35: 1 | I35: PC | J35: 45351
A36: Warranty | C36: 45293 | D36: DLS | E36: 10867661 | F36: OPTICAL SENSOR, OYKS950 REFL.LS M. HGA | G36: Position marker sensor | H36: 2 | I36: PC | J36: 45351
A37: NIKE ORDER | C37: 45648 | D37: 밀뱅코리아 | E37: 10849086_01 | F37: SCANNER, Cognex, DM280 | G37: 바코드 스캐너 | H37: 2 | I37: PC | J37: 45315
A38: Warranty | C38: 45293 | D38: DLS | E38: 10849086_01 | F38: SCANNER, Cognex, DM280 | G38: 바코드 스캐너 | H38: 1 | I38: PC | J38: 45351
A39: NIKE ORDER | C39: 견적요청중 | D39: DLS | E39: Unknown | F39: Vario timing belt | G39: 바리오 폭 조정 타이밍 벨트 | H39: 20 | I39: PC
A40: Warranty | C40: 45287 | D40: DLS | E40: 85365019 | F40: INDUCTIVE SENSOR, I18H022 20MM M18 | G40: 셔틀 하부 크로스 레일 감지 | H40: 1 | I40: PC | J40: 45378
A41: Warranty | C41: 45293 | D41: DLS | E41: 10547019_03 | F41: SUPERCAPACITOR EBG V2 -M, OSR_EVO | G41: SEM (셔틀 22번 교체) | H41: 1 | I41: PC | J41: 45351
A42: Warranty | D42: DLS | E42: 10547019_03 | F42: SUPERCAPACITOR EBG V2 -M, OSR_EVO | G42: SEM (셔틀 72번 교체) | H42: 1 | I42: PC
A43: NIKE ORDER | C43: 45295 | D43: DLS | E43: 10395761_01_0016 | F43: Telescopic unit chain | G43: 텔레스코프 체인 | H43: 5 | I43: PC | J43: 45351
A44: NIKE ORDER | C44: 45295 | D44: DLS | E44: 10446264 | F44: POWER SUPPLY UNIT, TDR-960-24V 40A | G44: Shuttle 전원 공급 파워서플라이 (24V) | H44: 3 | I44: PC | J44: 45351
A45: NIKE ORDER | C45: 45295 | D45: DLS | E45: 10218312 | F45: POWER SUPPLY UNIT, TDR-960-48V 20A | G45: Shuttle 전원 공급 파워서플라이 (48V) | H45: 3 | I45: PC | J45: 45351
A46: NIKE ORDER | C46: 45295 | D46: DLS | E46: 10609544_02_0001 | F46: ACCESS CONCEPT LZYL=4510 LINKS 1E V2 … | G46: KNAPP LOCK 장치 | H46: 3 | I46: PC | J46: 45351
A47: NIKE ORDER | D47: DLS | E47: 10609544_02_0001 | F47: ACCESS CONCEPT LZYL=4510 LINKS 1E V2 … | G47: KNAPP LOCK 장치 | H47: 5 | I47: PC | J47: 45338
A48: NIKE ORDER | C48: 45295 | D48: DLS | E48: 10505322_01 | F48: ACCESS CONCEPT EMERGENCY E -KPL, K_LOCK | G48: KNAPP 비상 LOCK 장치 | H48: 2 | I48: PC | J48: 45351
A49: NIKE ORDER | C49: 45295 | D49: DLS | E49: 10867661 | F49: OPTICAL SENSOR, OYKS950 REFL.LS M. HGA | G49: Position marker sensor | H49: 10 | I49: PC | J49: 45338
A50: NIKE ORDER | C50: 45295 | D50: DLS | E50: 10217650 | F50: PILZ Safety switch | G50: 랙 통로 Door safety switch | H50: 10 | I50: PC | J50: 45351
A51: NIKE ORDER | C51: 45295 | D51: DLS | E51: 10764610_01 | F51: CURRENT COLLECTOR, 0815 2P1PH 35A REV... | G51: 커런트 컬렉터 | H51: 30 | I51: PC | J51: 45351
A52: NIKE ORDER | C52: 45295 | D52: DLS | E52: 10200757 | F52: 2. Hexagon nut | G52: 사이드 가이드 휠 고정 볼트 | H52: 100 | I52: PC | J52: 45351
A53: NIKE ORDER | C53: 45295 | D53: DLS | E53: 10634710_01 | F53: 3. Vibration buffer | G53: 사이드 가이드 휠 버퍼 | H53: 100 | I53: PC | J53: 45351
A54: NIKE ORDER | C54: 45295 | D54: DLS | E54: 10679338_01 | F54: 4. Sideguide wheel | G54: 사이드 가이드 휠 | H54: 100 | I54: PC | J54: 45351
A55: NIKE ORDER | C55: 45295 | D55: DLS | E55: 10611156_02 | F55: Bracket (Front/Rear Left side) | G55: 사이드 가이드 휠 브라켓 | H55: 40 | I55: PC | J55: 45351
A56: NIKE ORDER | C56: 45295 | D56: DLS | E56: 10611156_03 | F56: Bracket (Front/Rear Right side) | G56: 사이드 가이드 휠 브라켓 | H56: 40 | I56: PC | J56: 45351
A57: NIKE ORDER | C57: 45295 | D57: DLS | E57: 10409303 | F57: Inductive sensor, I18H022 20MM M18 | G57: 사이드 가이드 휠 브라켓 | H57: 10 | I57: PC | J57: 45338
A58: NIKE ORDER | C58: 45295 | D58: DLS | E58: 10519144 | F58: INDUCTIVE SENSOR, SICK IMA18-20NE1ZC0K | G58: 셔틀 하부 크로스 레일 감지 센서 | H58: 10 | I58: PC | J58: 45338
A59: NIKE ORDER | D59: DLS | F59: Suttle 2set | G59: 셔틀 스페어 | H59: 2 | I59: PC | J59: 45314
A60: Warranty | C60: 45320 | D60: DLS | E60: 10849086_01 | F60: SCANNER, Cognex, DM280 | G60: 스캐너 | H60: 1 | I60: PC | J60: 45351
A61: Warranty | C61: 45320 | D61: DLS | E61: 10395273 | F61: INDUCTIVE SENSOR, I1BH011 3MM STIRN OE. / Retainer sensor | G61: 리테이너 감지센서(짧은선) | H61: 1 | I61: PC | J61: 45378
A62: Warranty | C62: 45320 | D62: DLS | E62: 10395201_01 | F62: STEPPER MOTOR HSY223-F06C + PX28S-16,... / Retainer motor | G62: 리테이너 모터 | H62: 1 | I62: PC | J62: 45378
A63: Warranty | C63: 45320 | D63: DLS | F63: SAFETY SWITCH. PSEN MA1.4P-50/MA1.4-MM | G63: 도어 안전 스위치 (노란색) | H63: 2 | I63: PC | J63: 45338
A64: NIKE ORDER | C64: 45344 | D64: DLS | E64: 10408341 | F64: INCREMENTAL ENCODER, DBS36E-BBAP00S43 | G64: 셔틀 주행 휠 엔코더 | H64: 4 | I64: PC | J64: 45378
A65: NIKE ORDER | C65: 45344 | D65: DLS | E65: 10395201_01 | F65: STEPPER MOTOR HSY223-F06C + PX28S-16,... | G65: 리테이터 모터 | H65: 4 | I65: PC | J65: 45378
A66: NIKE ORDER | C66: 45363 | D66: DLS | E66: 10404892 | F66: RFID READER, IQT1-FP-R4-V1 | G66: 셔틀 RFID 리터 | H66: 2 | I66: PC | J66: 45408
A67: Warranty | C67: 45363 | D67: DLS | E67: 10411039_01 | F67: LIFT DRIVE UNIT E60H4+EMT245 ELR 48VDC | G67: 셔틀 리프트 모터 | H67: 1 | I67: PC | J67: 45378
A68: Warranty | C68: 45363 | D68: DLS | E68: 10404892 | F68: RFID READER, IQT1-FP-R4-V1 | G68: 셔틀 RFID 리터 | H68: 1 | I68: PC | J68: 45378
A69: Warranty | D69: DLS | E69: 10395527_01_0017 | F69: Y-AXIS EBG_QFW -S, OSR, EVO | H69: 1 | I69: PC | J69: 45415
A70: Warranty | D70: DLS | E70: 10402682_01 | F70: ENCODER EBG_QFW -M, OSR_EVO | G70: 셔틀 엔코더 | H70: 1 | I70: PC | J70: 45415
A71: Warranty | C71: 45320 | D71: DLS | E71: 10411039_01 | F71: LIFT DRIVE UNIT E60H4+EMT245 ELR 48VDC | G71: LIFT DRIVE UNIT E60H4+EMT245 ELR 48VDC | H71: 1 | I71: PC | J71: 45415
A72: Warranty | C72: 45343 | D72: DLS | E72: 10404892 | F72: RFID READER, IQT1-FP-R4-V1 | G72: 셔틀 RFID 리더 | H72: 1 | I72: PC | J72: 45415
A73: Warranty | C73: 45363 | D73: DLS | E73: 10411034_01 | F73: GEAR MOTOR ELR 220/10/3500 48V BL70S-... | G73: 크로스 주행 모터 | H73: 1 | I73: PC | J73: 45415
A74: Warranty | D74: DLS | E74: 10412613_02 | F74: CORNER ELEMENT EBG -M, OSR_EVO | H74: 1 | I74: PC | J74: 45415
A75: Warranty | C75: 45478 | D75: DLS | E75: 10404892 | F75: RFID READER, IQT1-FP-R4-V1 | G75: 셔틀 RFID 리더 | H75: 1 | I75: PC | J75: 45511
A76: Warranty | C76: 45478 | D76: DLS | E76: 10867661 | F76: OPTICAL SENSOR, OYKS950 REFL.LS M. HGA | G76: Position marker sensor | H76: 5 | I76: PC | J76: 45511
A77: Warranty | C77: 45478 | D77: DLS | E77: 10411034_01 | F77: GEAR MOTOR ELR 220/10/3500 48V BL70S-... | G77: 크로스 주행 모터 (모터2) | H77: 1 | I77: PC | J77: 45511
A78: Warranty | C78: 45478 | D78: DLS | E78: 10408341 | F78: INCREMENTAL ENCODER, DBS36E-BBAP00S43 | G78: 셔틀 엔코더 | H78: 1 | I78: PC | J78: 45511
A79: Warranty | C79: 45478 | D79: DLS | E79: 10409303 | F79: INDUCTIVE SENSOR, I18H022 20MM M18 | H79: 1 | I79: PC | J79: 45511
A80: Warranty | C80: 45499 | D80: DLS | E80: 10217650 | F80: Door safety switch, PILZ 506334 (506301+506308) | G80: 랙 통로 도어 안전 스위치 | H80: 1 | I80: PC | J80: 45576
A81: Warranty | C81: 45499 | D81: DLS | E81: 10395279 | F81: INDUCTIVE SENSOR, I1BH013 3MM STIRN OE. | G81: 리테이너 감지센서(긴 선) | H81: 1 | I81: PC | J81: 45576
A82: Warranty | C82: 45499 | D82: DLS | E82: 10404892 | F82: RFID READER, IQT1-FP-R4-V1 | G82: RFID 리더 | H82: 1 | I82: PC | J82: 45576
A83: Warranty | C83: 45499 | D83: DLS | E83: 10404892 | F83: RFID READER, IQT1-FP-R4-V1 | G83: RFID 리더 | H83: 1 | I83: PC | J83: 45576
A84: NIKE ORDER | B84: 구경모 | C84: 45554 | D84: DLS | E84: 10416998_01 | F84: ACCESS CONCEPT, ACTUATOR V1 E -M, OSR_EVO | G84: KNAPP LOCK (LIGHT CURTAIN 전 LOCK) | H84: 3 | I84: PC | J84: 12월11일
A85: NIKE ORDER | B85: 구경모 | C85: 45554 | D85: DLS | E85: 10567316_01 | F85: BOGIE WHEEL, QFW ABLF EBG, OSR_EVO | G85: 크로스 통로 주행 휠 | H85: 20 | I85: PC | J85: 45581
A86: NIKE ORDER | B86: 구경모 | C86: 45554 | D86: DLS | E86: 10764610_01 | F86: CURRENT COLLECTOR, 0815 2P1PH 35A REV… | G86: 커런트 컬렉터 | H86: 30 | I86: PC | J86: 45581
A87: NIKE ORDER | B87: 구경모 | C87: 45554 | D87: DLS | E87: 10725130_01_0002 | F87: REMOTE CONTROL, HBC-STEUERUNG 308 QUA… | G87: 호이스트 리모컨 | H87: 1 | I87: PC | J87: 12월11일
A88: NIKE ORDER | B88: 구경모 | C88: 45554 | D88: DLS | E88: 10395279 | F88: INDUCTIVE SENSOR, I1BH013 3MM STIRN OE. | G88: 리테이너 감지센서(긴 선) | H88: 5 | I88: PC | J88: 12월11일
A89: NIKE ORDER | B89: 구경모 | C89: 45554 | D89: DLS | E89: 10907771_02 | F89: SIDE GUIDE V8 EBG -M, OSR_EVO | G89: 사이드 가이드 휠 일체형(개선품) | H89: 40 | I89: PC | J89: 12월11일
A90: NIKE ORDER | B90: 구경모 | C90: 45554 | D90: DLS | E90: 10907771_03 | F90: SIDE GUIDE V8 EBG -M, OSR_EVO | G90: 사이드 가이드 휠 일체형(개선품) | H90: 40 | I90: PC | J90: 12월11일
A91: NIKE ORDER | B91: 구경모 | C91: 45554 | D91: DLS | E91: 10631253_01 | F91: SUPPORT, LONGITUDINAL RFID_TAG -M, OS… | G91: RFID 트랜스폰더_종방향(브라켓포함) | H91: 20 | I91: PC | J91: 12월11일
A92: NIKE ORDER | B92: 구경모 | C92: 45554 | D92: DLS | E92: 10631252_01 | F92: SUPPORT, CROSS RFID_TAG -M, OSR_EVO | G92: RFID 트랜스폰더_크로스영역(브라켓포함) | H92: 20 | I92: PC | J92: 12월11일
A93: NIKE ORDER | B93: 구경모 | C93: 45638 | D93: DLS | E93: 10202556 | F93: REFLECTOR, 23X39 M4X8.4 E393-60 | G93: 광센서 반사판 | H93: 30 | I93: PC | J93: 45699
A94: NIKE ORDER | B94: 구경모 | C94: 45638 | D94: DLS | E94: 10207112_01 | F94: LUBRICANT, KNAPPSPRAY2 MOTOREX 2000 | G94: 구리스 | H94: 5 | I94: PC | J94: 45741
A95: NIKE ORDER | B95: 권오준 | C95: 45638 | D95: DLS | E95: 10662772_01 | F95: I/O MODULE, ASI VBA-3E3A-G20-ZEL/E2L-… | G95: 3in 3out, 롤러 컨베이어 모터 모듈(ASI) | H95: 5 | I95: PC | J95: 45741
A96: NIKE ORDER | B96: 권오준 | C96: 45638 | D96: DLS | E96: 10662775_01 | F96: MOTOR MODULE, ASI VBA-4E3A-G20-ZEL/M1… | G96: 2in 2out, 롤러 컨베이어 모터 모듈(ASI) | H96: 5 | I96: PC | J96: 45699
A97: NIKE ORDER | B97: 권오준 | C97: 45638 | D97: DLS | E97: 10219379 | F97: COMBINED MODULE, 1DI 1DQ G10 ASI | G97: ASI 모듈 | H97: 3 | I97: PC | J97: 45741
A98: NIKE ORDER | B98: 권오준 | C98: 45638 | D98: DLS | E98: 10219436 | F98: INPUT MODULE, 2DI G10 ASI SLAVE ASI-DC | G98: ASI 모듈 | H98: 3 | I98: PC | J98: 45741
A99: NIKE ORDER | B99: 권오준 | C99: 45638 | D99: DLS | E99: 10219383 | F99: INPUT MODULE, 2DI G10 ASI SLAVE | G99: ASI 모듈 | H99: 3 | I99: PC | J99: 45741
A100: NIKE ORDER | B100: 권오준 | C100: 45638 | D100: DLS | E100: 10219504 | F100: PASSIVE DISTRIBUTOR, G10 ASI MIT SICH... | G100: ASI 모듈 | H100: 3 | I100: PC | J100: 45741
A101: NIKE ORDER | B101: 구경모 | C101: 45638 | D101: DLS | E101: 10223711 | F101: INPUT MODULE, 4/8 F-DI DC24V ET200SP | G101: 6ES7136-6BA01-0CA0 | H101: 1 | I101: PC | J101: 45741
A102: NIKE ORDER | B102: 구경모 | C102: 45638 | D102: DLS | E102: 10395586 | F102: CONNECTION BOX, PN KOMPAKT | G102: 6AV2125-2AE03-0AX0 | H102: 2 | I102: PC | J102: 45741
...

Sheet ASRS parts replacement
N1: 0
N2: 1 | O2: 2 | P2: 3 | Q2: 4 | R2: 5 | S2: 6 | T2: 7 | U2: 8 | V2: 9 | W2: 10 | X2: 11 | Y2: 12 | Z2: 13 | AA2: 14 | AB2: 15 | AC2: 16 | AD2: 17 | AE2: 18 | AF2: 19 | AG2: 20 | AH2: 21 | AI2: 22 | AJ2: 23 | AK2: 24 | AL2: 25 | AM2: 26 | AN2: 27 | AO2: 28 | AP2: 29 | AQ2: 30 | AR2: 31 | AS2: 32 | AT2: 33 | AU2: 34 | AV2: 35 | AW2: 36 | AX2: 37 | AY2: 38 | AZ2: 39 | BA2: 40 | BB2: 41 | BC2: 42 | BD2: 43 | BE2: 44 | BF2: 45 | BG2: 46 | BH2: 47 | BI2: 48 | BJ2: 49 | BK2: 50 | BL2: 51 | BM2: 52 | BN2: 53 | BO2: 54 | BP2: 55 | BQ2: 56 | BR2: 57 | BS2: 58 | BT2: 59 | BU2: 60 | BV2: 61 | BW2: 62 | BX2: 63 | BY2: 64 | BZ2: 65 | CA2: 66 | CB2: 67 | CC2: 68 | CD2: 69 | CE2: 70 | CF2: 71 | CG2: 72 | CH2: 73 | CI2: 74 | CJ2: 75 | CK2: 76 | CL2: 77 | CM2: 78 | CN2: 79 | CO2: 80 | CP2: 81 | CQ2: 82 | CR2: 83 | CS2: 84 | CT2: 85 | CU2: 86 | CV2: 87 | CW2: 88 | CX2: 89 | CY2: 90 | CZ2: 91 | DA2: 92 | DB2: 93 | DC2: 94 | DD2: 95 | DE2: 96
L3: =COUNTIF(N3:DC3,N1) -> 1 | M3: Current collector(랙통로) | N3: =COUNTIFS($B:$B,N$2,$C:$C,$M3) -> 7 | O3: =COUNTIFS($B:$B,O$2,$C:$C,$M3) -> 6 | P3: =COUNTIFS($B:$B,P$2,$C:$C,$M3) -> 7 | Q3: =COUNTIFS($B:$B,Q$2,$C:$C,$M3) -> 5 | R3: =COUNTIFS($B:$B,R$2,$C:$C,$M3) -> 2 | S3: =COUNTIFS($B:$B,S$2,$C:$C,$M3) -> 2 | T3: =COUNTIFS($B:$B,T$2,$C:$C,$M3) -> 6 | U3: =COUNTIFS($B:$B,U$2,$C:$C,$M3) -> 3 | ... DE3: =COUNTIFS($B:$B,DE$2,$C:$C,$M3) -> 0
L4: =COUNTIF(N4:DC4,N1) -> 32 | M4: Current collector(크로스) | N4: =COUNTIFS($B:$B,N$2,$C:$C,$M4) -> 1 | O4: =COUNTIFS($B:$B,O$2,$C:$C,$M4) -> 1 | P4: =COUNTIFS($B:$B,P$2,$C:$C,$M4) -> 2 | Q4: =COUNTIFS($B:$B,Q$2,$C:$C,$M4) -> 1 | R4: =COUNTIFS($B:$B,R$2,$C:$C,$M4) -> 1 | S4: =COUNTIFS($B:$B,S$2,$C:$C,$M4) -> 0 | T4: =COUNTIFS($B:$B,T$2,$C:$C,$M4) -> 0 | U4: =COUNTIFS($B:$B,U$2,$C:$C,$M4) -> 1 | ... DE4: =COUNTIFS($B:$B,DE$2,$C:$C,$M4) -> 0
L5: =COUNTIF(N5:DC5,N1) -> 0 | M5: TOTAL | N5: =SUM(N3:N4) -> 8 | O5: =SUM(O3:O4) -> 7 | P5: =SUM(P3:P4) -> 9 | Q5: =SUM(Q3:Q4) -> 6 | R5: =SUM(R3:R4) -> 3 | S5: =SUM(S3:S4) -> 2 | T5: =SUM(T3:T4) -> 6 | U5: =SUM(U3:U4) -> 4 | ... DE5: =SUM(DE3:DE4) -> 0 | DF5: =SUM(N5:DE5) -> 486
A14: Date | B14: Shuttle# | C14: Parts I | D14: Parts II | E14: Parts III | F14: Material Number | G14: Remark | H14: Used days | I14: NEW/USED | J14: Warranty | K14: Warranty 요청 | L14: 세로 막대형1
A15: 46148 | B15: 37 | C15: Current collector(랙통로) | D15: CURRENT COLLECTOR, 0815 2P1PH 35A REV... | E15: 종방향 | F15: =VLOOKUP(D15,Parts!D:N, 11,FALSE) -> 10764610_01 | G15: 불량으로 인한 교체 | H15: =TODAY()-표1[[#This Row],[Date]] -> 5 | I15: NEW
A16: 46146 | B16: 90 | C16: Current collector(랙통로) | D16: CURRENT COLLECTOR, 0815 2P1PH 35A REV... | E16: 종방향 | F16: =VLOOKUP(D16,Parts!D:N, 11,FALSE) -> 10764610_01 | G16: 불량으로 인한 교체 | H16: =TODAY()-표1[[#This Row],[Date]] -> 7 | I16: NEW
A17: 46134 | B17: 53 | C17: Current collector(랙통로) | D17: CURRENT COLLECTOR, 0815 2P1PH 35A REV... | E17: 종방향 | F17: =VLOOKUP(D17,Parts!D:N, 11,FALSE) -> 10764610_01 | G17: 마모로 인한 교체 | H17: =TODAY()-표1[[#This Row],[Date]] -> 19 | I17: NEW
A18: 46134 | B18: 53 | C18: Cover | D18: CORNER ELEMENT EBG -M, OSR_EVO (rear left side) | E18: Corner element (Corner cover)_rear left side | F18: =VLOOKUP(D18,Parts!D:N, 11,FALSE) -> 10412613_02 | G18: 파손으로 교체 | H18: =TODAY()-표1[[#This Row],[Date]] -> 19 | I18: NEW
A19: 46134 | B19: 53 | C19: Wheel | D19: BOGIE WHEEL, LFW ABLF EBG OSR_EVO | E19: 종방향 주행 휠 | F19: =VLOOKUP(D19,Parts!D:N, 11,FALSE) -> 10567315_01 | G19: 마모로 인한 교체 | H19: =TODAY()-표1[[#This Row],[Date]] -> 19 | I19: NEW
A20: 46134 | B20: 53 | C20: Sideguide wheel | D20: SIDE GUIDE V8 EBG -M, OSR_EVO (Front left side, Rear right side) | E20: 2EA | F20: =VLOOKUP(D20,Parts!D:N, 11,FALSE) -> 10907771_02 | G20: 파손으로 4ea 교체 | H20: =TODAY()-표1[[#This Row],[Date]] -> 19 | I20: NEW
A21: 46134 | B21: 53 | C21: Sideguide wheel | D21: SIDE GUIDE V8 EBG -M, OSR_EVO (Front right side, Rear left side) | E21: 2EA | F21: =VLOOKUP(D21,Parts!D:N, 11,FALSE) -> 10907771_03 | G21: 파손으로 4ea 교체 | H21: =TODAY()-표1[[#This Row],[Date]] -> 19 | I21: NEW
A22: 46129 | B22: 51 | C22: Wheel | D22: BOGIE WHEEL, LFW ABLF EBG OSR_EVO | E22: 종방향 주행 휠 | F22: =VLOOKUP(D22,Parts!D:N, 11,FALSE) -> 10567315_01 | G22: 마모로 4EA 교체 | H22: =TODAY()-표1[[#This Row],[Date]] -> 24 | I22: NEW
A23: 46129 | B23: 51 | C23: Sideguide wheel | D23: SIDE GUIDE V8 EBG -M, OSR_EVO (Front left side, Rear right side) | E23: 2EA | F23: =VLOOKUP(D23,Parts!D:N, 11,FALSE) -> 10907771_02 | G23: (PM) 개선품 교체 | H23: =TODAY()-표1[[#This Row],[Date]] -> 24 | I23: NEW
A24: 46129 | B24: 51 | C24: Sideguide wheel | D24: SIDE GUIDE V8 EBG -M, OSR_EVO (Front right side, Rear left side) | E24: 2EA | F24: =VLOOKUP(D24,Parts!D:N, 11,FALSE) -> 10907771_03 | G24: (PM) 개선품 교체 | H24: =TODAY()-표1[[#This Row],[Date]] -> 24 | I24: NEW
A25: 46127 | B25: 66 | C25: Current collector(랙통로) | D25: CURRENT COLLECTOR, 0815 2P1PH 35A REV... | E25: 종방향 | F25: =VLOOKUP(D25,Parts!D:N, 11,FALSE) -> 10764610_01 | G25: 마모로 인한 교체 | H25: =TODAY()-표1[[#This Row],[Date]] -> 26 | I25: NEW
A26: 46125 | B26: 40 | C26: Current collector(랙통로) | D26: CURRENT COLLECTOR, 0815 2P1PH 35A REV... | E26: 종방향 | F26: =VLOOKUP(D26,Parts!D:N, 11,FALSE) -> 10764610_01 | G26: 불량으로 인한 교체 | H26: =TODAY()-표1[[#This Row],[Date]] -> 28 | I26: NEW
... A40: 46104 | B40: 24 | C40: SEM | D40: SUPERCAPACITOR EBG V2 -M, OSR_EVO | E40: 안전 확장 모듈 Safety Extension Module | F40: =VLOOKUP(D40,Parts!D:N, 11,FALSE) -> 10547019_03 | G40: EVOS-0035 error 전원공급 불량으로 교체 | H40: =TODAY()-표1[[#This Row],[Date]] -> 49 | I40: NEW
A41: 46104 | B41: 24 | C41: Current collector(랙통로) | D41: CURRENT COLLECTOR, 0815 2P1PH 35A REV... | E41: 종방향 | F41: =VLOOKUP(D41,Parts!D:N, 11,FALSE) -> 10764610_01 | H41: =TODAY()-표1[[#This Row],[Date]] -> 49 | I41: NEW
A42: 46100 | B42: 57 | C42: Motor | D42: GEAR MOTOR ELRkw/33kw/3000 48V BL42YS-48V... | E42: 바리오 센터링 모터 (모터5) | F42: =VLOOKUP(D42,Parts!D:N, 11,FALSE) -> 10540023_01 | G42: EVOS-0022 Error | H42: =TODAY()-표1[[#This Row],[Date]] -> 53 | I42: NEW
A43: 46099 | B43: 57 | C43: Printed Circuit Board | D43: ASSEMB. PRINTED CIRCUIT BOARD, SHUTTL... Replacement for 10676955_02 | E43: 셔틀 인쇄 회로 기판 | F43: =VLOOKUP(D43,Parts!D:N, 11,FALSE) -> 10676955_08 | G43: EVOS-0022 Error | H43: =TODAY()-표1[[#This Row],[Date]] -> 54 | I43: NEW
A44: 46098 | B44: 59 | C44: Motor | D44: GEAR MOTOR ELR 220kw/10kw/3500 48V BL70S-... | E44: 횡방향 주행 모터 (모터2) | F44: =VLOOKUP(D44,Parts!D:N, 11,FALSE) -> 10411034_01 | G44: 불량(케이블 단선)으로 인한 교체(Motor2 error) | H44: =TODAY()-표1[[#This Row],[Date]] -> 55 | I44: NEW
A45: 46098 | B45: 28 | C45: Current collector(랙통로) | D45: CURRENT COLLECTOR, 0815 2P1PH 35A REV... | E45: 종방향 | F45: =VLOOKUP(D45,Parts!D:N, 11,FALSE) -> 10764610_01 | G45: 불량으로 인한 교체 | H45: =TODAY()-표1[[#This Row],[Date]] -> 55 | I45: NEW
A46: 46097 | B46: 26 | C46: Current collector(랙통로) | D46: CURRENT COLLECTOR PAIR 1 Set | E46: 종방향 | F46: =VLOOKUP(D46,Parts!D:N, 11,FALSE) -> 1 | G46: 마모로 인한 교체 | H46: =TODAY()-표1[[#This Row],[Date]] -> 56 | I46: NEW
A47: 46093 | B47: 29 | C47: Current collector(랙통로) | D47: CURRENT COLLECTOR PAIR 1 Set | E47: 종방향 | F47: =VLOOKUP(D47,Parts!D:N, 11,FALSE) -> 1 | G47: 마모로 인한 교체 | H47: =TODAY()-표1[[#This Row],[Date]] -> 60 | I47: NEW
A48: 46092 | B48: 52 | C48: Current collector(랙통로) | D48: CURRENT COLLECTOR, 0815 2P1PH 35A REV... | E48: 종방향 | F48: =VLOOKUP(D48,Parts!D:N, 11,FALSE) -> 10764610_01 | G48: 파손으로 인한 교체 | H48: =TODAY()-표1[[#This Row],[Date]] -> 61 | I48: NEW
A49: 46091 | B49: 52 | C49: Sideguide wheel | D49: SIDE GUIDE V8 EBG -M, OSR_EVO (Front left side, Rear right side) | E49: 2EA | F49: =VLOOKUP(D49,Parts!D:N, 11,FALSE) -> 10907771_02 | G49: (PM) 개선품 교체 | H49: =TODAY()-표1[[#This Row],[Date]] -> 62 | I49: NEW
A50: 46091 | B50: 52 | C50: Sideguide wheel | D50: SIDE GUIDE V8 EBG -M, OSR_EVO (Front right side, Rear left side) | E50: 2EA | F50: =VLOOKUP(D50,Parts!D:N, 11,FALSE) -> 10907771_03 | G50: (PM) 개선품 교체 | H50: =TODAY()-표1[[#This Row],[Date]] -> 62 | I50: NEW
A51: 46091 | B51: 52 | C51: Current collector(랙통로) | D51: CURRENT COLLECTOR PAIR 1 Set | E51: 횡방향 | F51: =VLOOKUP(D51,Parts!D:N, 11,FALSE) -> 1 | G51: (PM)마모로 인한 교체 | H51: =TODAY()-표1[[#This Row],[Date]] -> 62 | I51: NEW
A52: 46091 | B52: 52 | C52: Current collector(랙통로) | D52: CURRENT COLLECTOR PAIR 1 Set | E52: 종방향 | F52: =VLOOKUP(D52,Parts!D:N, 11,FALSE) -> 1 | G52: (PM)마모로 인한 교체 | H52: =TODAY()-표1[[#This Row],[Date]] -> 62 | I52: NEW
A53: 46090 | C53: RFID | D53: MOUNTING KIT RAL1016 RFID R_KG -M, OS… | E53: RFID 트랜스폰더_HB-B 크로스구간(노란색 브라켓포함) 2EA | F53: =VLOOKUP(D53,Parts!D:N, 11,FALSE) -> 10428896_01_0002 | G53: 3통로 16Lv C01,C03 파손으로 교체 | H53: =TODAY()-표1[[#This Row],[Date]] -> 63 | I53: NEW
A54: 46089 | B54: 50 | C54: Current collector(랙통로) | D54: CURRENT COLLECTOR PAIR 1 Set | E54: 횡방향 | F54: =VLOOKUP(D54,Parts!D:N, 11,FALSE) -> 1 | G54: (PM)마모로 인한 교체 | H54: =TODAY()-표1[[#This Row],[Date]] -> 64 | I54: NEW
A55: 46089 | B55: 50 | C55: Current collector(랙통로) | D55: CURRENT COLLECTOR PAIR 1 Set | E55: 종방향 | F55: =VLOOKUP(D55,Parts!D:N, 11,FALSE) -> 1 | G55: (PM)마모로 인한 교체 | H55: =TODAY()-표1[[#This Row],[Date]] -> 64 | I55: NEW
A56: 46087 | B56: 50 | C56: Sideguide wheel | D56: SIDE GUIDE V8 EBG -M, OSR_EVO (Front left side, Rear right side) | E56: 2EA | F56: =VLOOKUP(D56,Parts!D:N, 11,FALSE) -> 10907771_02 | G56: (PM)파손으로 4EA 교체 | H56: =TODAY()-표1[[#This Row],[Date]] -> 66 | I56: NEW
A57: 46087 | B57: 50 | C57: Sideguide wheel | D57: SIDE GUIDE V8 EBG -M, OSR_EVO (Front right side, Rear left side) | E57: 2EA | F57: =VLOOKUP(D57,Parts!D:N, 11,FALSE) -> 10907771_03 | G57: (PM)파손으로 4EA 교체 | H57: =TODAY()-표1[[#This Row],[Date]] -> 66 | I57: NEW
A58: 46086 | B58: 49 | C58: Wheel | D58: BOGIE WHEEL, LFW ABLF EBG OSR_EVO | E58: 종방향 주행 휠 | F58: =VLOOKUP(D58,Parts!D:N, 11,FALSE) -> 10567315_01 | G58: (PM)마모로 4EA 교체 | H58: =TODAY()-표1[[#This Row],[Date]] -> 67 | I58: NEW
A59: 46086 | B59: 49 | C59: Current collector(랙통로) | D59: CURRENT COLLECTOR, 0815 2P1PH 35A REV... | E59: 종방향 | F59: =VLOOKUP(D59,Parts!D:N, 11,FALSE) -> 10764610_01 | G59: (PM)마모,유닛 전체 교체(Knapp) | H59: =TODAY()-표1[[#This Row],[Date]] -> 67 | I59: NEW
A60: 46086 | B60: 92 | C60: Sideguide wheel | D60: SIDE GUIDE V8 EBG -M, OSR_EVO (Front left side, Rear right side) | E60: Front Left 1EA | F60: =VLOOKUP(D60,Parts!D:N, 11,FALSE) -> 10907771_02 | G60: 파손으로 인한 교체 | H60: =TODAY()-표1[[#This Row],[Date]] -> 67 | I60: NEW
A61: 46086 | B61: 45 | C61: Current collector(랙통로) | D61: CURRENT COLLECTOR PAIR 1 Set | E61: 종방향 | F61: =VLOOKUP(D61,Parts!D:N, 11,FALSE) -> 1 | G61: 마모로 인한 교체 | H61: =TODAY()-표1[[#This Row],[Date]] -> 67 | I61: NEW
A62: 46077 | B62: 87 | C62: Wheel | D62: BOGIE WHEEL, QFW ABLF EBG, OSR_EVO | E62: 횡방향 주행 휠 | F62: =VLOOKUP(D62,Parts!D:N, 11,FALSE) -> 10567316_01 | G62: 마모로 4EA 교체 | H62: =TODAY()-표1[[#This Row],[Date]] -> 76 | I62: NEW
A63: 46077 | B63: 87 | C63: Sideguide wheel | D63: SIDE GUIDE V8 EBG -M, OSR_EVO (Front left side, Rear right side) | E63: 2EA | F63: =VLOOKUP(D63,Parts!D:N, 11,FALSE) -> 10907771_02 | G63: 파손으로 4EA 교체 | H63: =TODAY()-표1[[#This Row],[Date]] -> 76 | I63: NEW
A64: 46077 | B64: 87 | C64: Sideguide wheel | D64: SIDE GUIDE V8 EBG -M, OSR_EVO (Front right side, Rear left side) | E64: 2EA | F64: =VLOOKUP(D64,Parts!D:N, 11,FALSE) -> 10907771_03 | G64: 파손으로 4EA 교체 | H64: =TODAY()-표1[[#This Row],[Date]] -> 76 | I64: NEW
A65: 46056 | B65: 5 | C65: Sideguide wheel | D65: SIDE GUIDE V8 EBG -M, OSR_EVO (Front left side, Rear right side) | E65: 2EA | F65: =VLOOKUP(D65,Parts!D:N, 11,FALSE) -> 10907771_02 | G65: 파손으로 4EA 교체 | H65: =TODAY()-표1[[#This Row],[Date]] -> 97 | I65: NEW
... A70: 46056 | B70: 68 | C70: Motor | D70: GEAR MOTOR ELR 220kw/10kw/3500 48V BL70S-... | E70: 횡방향 주행 모터 (모터2) | F70: =VLOOKUP(D70,Parts!D:N, 11,FALSE) -> 10411034_01 | G70: 크로스 주행 시 소음 발생으로 인한 교체 | H70: =TODAY()-표1[[#This Row],[Date]] -> 97 | I70: NEW
A71: 46055 | B71: 41 | C71: SEM | D71: SUPERCAPACITOR EBG V2 -M, OSR_EVO | F71: =VLOOKUP(D71,Parts!D:N, 11,FALSE) -> 10547019_03 | G71: Shuttle LED Yellow : red 점등(Safe state : CPU error) | H71: =TODAY()-표1[[#This Row],[Date]] -> 98 | I71: NEW
A72: 46055 | B72: 5 | C72: Cover | D72: CORNER ELEMENT EBG -M, OSR_EVO (Rear right side) | E72: Corner element (Corner cover)_front left side | F72: =VLOOKUP(D72,Parts!D:N, 11,FALSE) -> 10412613_03 | G72: 파손으로 교체 | H72: =TODAY()-표1[[#This Row],[Date]] -> 98 | I72: NEW
A73: 46051 | B73: 44 | C73: Sensor | D73: OPTICAL SENSOR, OYKS950 REFL.LS M. HGA Replacement for 10409305 | E73: 교차로 중앙 센서/종방향 이동 마커 센서 | F73: =VLOOKUP(D73,Parts!D:N, 11,FALSE) -> 10867661 | G73: 크로싱구간에서 EVOS-0045 에러 발생으로 교체 | H73: =TODAY()-표1[[#This Row],[Date]] -> 102 | I73: NEW
A74: 46049 | B74: 92 | C74: RFID | D74: RFID READER, IQT1-FP-R4-V1 | E74: RFID 리더 | F74: =VLOOKUP(D74,Parts!D:N, 11,FALSE) -> 10404892 | G74: RFID Transponder 인식 불량으로 교체 | H74: =TODAY()-표1[[#This Row],[Date]] -> 104 | I74: NEW
A75: 46049 | B75: 27 | C75: Sensor | D75: OPTICAL SENSOR, OYKS950 REFL.LS M. HGA Replacement for 10409305 | E75: 교차로 중앙 센서/종방향 이동 마커 센서 | F75: =VLOOKUP(D75,Parts!D:N, 11,FALSE) -> 10867661 | G75: Carton Loading/Unloading 시 에러 발생, 셔틀 정위치 불량 의심하여 센서 교체 진행 | H75: =TODAY()-표1[[#This Row],[Date]] -> 104 | I75: NEW
A76: 46047 | B76: 92 | C76: Wheel | D76: BOGIE WHEEL, LFW ABLF EBG OSR_EVO | E76: 종방향 주행 휠 | F76: =VLOOKUP(D76,Parts!D:N, 11,FALSE) -> 10567315_01 | G76: 4EA 교체, 1통로C01과 1섹터 사이 단차에서 Front Right 가이드휠 바닥면 걸림으로 교체 | H76: =TODAY()-표1[[#This Row],[Date]] -> 106 | I76: NEW
A77: 46045 | B77: 90 | C77: Sideguide wheel | D77: SIDE GUIDE V8 EBG -M, OSR_EVO (Front left side, Rear right side) | E77: 2EA | F77: =VLOOKUP(D77,Parts!D:N, 11,FALSE) -> 10907771_02 | G77: 마모로 4EA 교체 | H77: =TODAY()-표1[[#This Row],[Date]] -> 108 | I77: NEW
A78: 46045 | B78: 90 | C78: Sideguide wheel | D78: SIDE GUIDE V8 EBG -M, OSR_EVO (Front right side, Rear left side) | E78: 2EA | F78: =VLOOKUP(D78,Parts!D:N, 11,FALSE) -> 10907771_03 | G78: 마모로 4EA 교체 | H78: =TODAY()-표1[[#This Row],[Date]] -> 108 | I78: NEW
A79: 46045 | B79: 90 | C79: Wheel | D79: BOGIE WHEEL, LFW ABLF EBG OSR_EVO | E79: 종방향 주행 휠 | F79: =VLOOKUP(D79,Parts!D:N, 11,FALSE) -> 10567315_01 | G79: 마모로 4EA 교체 | H79: =TODAY()-표1[[#This Row],[Date]] -> 108 | I79: NEW
A80: 46045 | B80: 90 | C80: Wheel | D80: BOGIE WHEEL, QFW ABLF EBG, OSR_EVO | E80: 횡방향 주행 휠 | F80: =VLOOKUP(D80,Parts!D:N, 11,FALSE) -> 10567316_01 | G80: 마모로 4EA 교체 | H80: =TODAY()-표1[[#This Row],[Date]] -> 108 | I80: NEW
A81: 46045 | B81: 30 | C81: Current collector(랙통로) | D81: CURRENT COLLECTOR, 0815 2P1PH 35A REV... | E81: 종방향 | F81: =VLOOKUP(D81,Parts!D:N, 11,FALSE) -> 10764610_01 | G81: 커넥터 그을림으로 인한 교체 | H81: =TODAY()-표1[[#This Row],[Date]] -> 108 | I81: NEW
A82: 46044 | B82: 27 | C82: Sideguide wheel | D82: SIDE GUIDE V8 EBG -M, OSR_EVO (Front left side, Rear right side) | E82: 2EA | F82: =VLOOKUP(D82,Parts!D:N, 11,FALSE) -> 10907771_02 | G82: 마모로 4EA 교체 | H82: =TODAY()-표1[[#This Row],[Date]] -> 109 | I82: NEW
A83: 46044 | B83: 27 | C83: Sideguide wheel | D83: SIDE GUIDE V8 EBG -M, OSR_EVO (Front right side, Rear left side) | E83: 2EA | F83: =VLOOKUP(D83,Parts!D:N, 11,FALSE) -> 10907771_03 | G83: 마모로 4EA 교체 | H83: =TODAY()-표1[[#This Row],[Date]] -> 109 | I83: NEW
... A92: 46041 | B92: 87 | C92: Current collector(랙통로) | D92: CURRENT COLLECTOR, 0815 2P1PH 35A REV... | E92: 종방향 | F92: =VLOOKUP(D92,Parts!D:N, 11,FALSE) -> 10764610_01 | G92: 커넥터 그을림으로 인한 교체 | H92: =TODAY()-표1[[#This Row],[Date]] -> 112 | I92: NEW
A93: 46037 | B93: 58 | C93: SEM | D93: SUPERCAPACITOR EBG V2 -M, OSR_EVO | F93: =VLOOKUP(D93,Parts!D:N, 11,FALSE) -> 10547019_03 | G93: EVOS-0045 Error | H93: =TODAY()-표1[[#This Row],[Date]] -> 116 | I93: NEW
A94: 46036 | B94: 38 | C94: Current collector(랙통로) | D94: CURRENT COLLECTOR PAIR 1 Set | E94: 종방향 | F94: =VLOOKUP(D94,Parts!D:N, 11,FALSE) -> 1 | G94: 3통로 C03 EVOS-0045 Error 및 마모로 교체 | H94: =TODAY()-표1[[#This Row],[Date]] -> 117 | I94: NEW
A95: 46036 | B95: 38 | C95: Current collector(크로스) | D95: CURRENT COLLECTOR PAIR 1 Set | E95: 횡방향 | F95: =VLOOKUP(D95,Parts!D:N, 11,FALSE) -> 1 | G95: 3통로 C03 EVOS-0045 Error | H95: =TODAY()-표1[[#This Row],[Date]] -> 117 | I95: NEW
A96: 46036 | B96: 82 | C96: Motor | D96: LIFT DRIVE UNIT E60H4+EMT245 ELR 48VDC | E96: Lifting Motor | F96: =VLOOKUP(D96,Parts!D:N, 11,FALSE) -> 10411039_01 | G96: 불량으로 교체 | H96: =TODAY()-표1[[#This Row],[Date]] -> 117 | I96: NEW
A97: 46035 | B97: 80 | C97: Wheel | D97: BOGIE WHEEL, LFW ABLF EBG OSR_EVO | E97: 종방향 주행 휠 | F97: =VLOOKUP(D97,Parts!D:N, 11,FALSE) -> 10567315_01 | G97: 마모로 4ea 교체 | H97: =TODAY()-표1[[#This Row],[Date]] -> 118 | I97: NEW
A98: 46031 | B98: 80 | C98: Cover | D98: CORNER ELEMENT EBG -M, OSR_EVO (Rear right side) | E98: Corner element (Corner cover)_front left side | F98: =VLOOKUP(D98,Parts!D:N, 11,FALSE) -> 10412613_03 | G98: 파손으로 교체 | H98: =TODAY()-표1[[#This Row],[Date]] -> 122 | I98: NEW
A99: 46031 | B99: 80 | C99: Wheel | D99: BOGIE WHEEL, QFW ABLF EBG, OSR_EVO | E99: 횡방향 주행 휠 | F99: =VLOOKUP(D99,Parts!D:N, 11,FALSE) -> 10567316_01 | G99: 마모로 4ea 교체 | H99: =TODAY()-표1[[#This Row],[Date]] -> 122 | I99: NEW
A100: 46031 | B100: 80 | C100: Sensor | D100: INDUCTIVE SENSOR, SICK IMA18-20NE1ZC0K | E100: Lifting height sensor(리프팅 높이 센서) 셔틀 하부 크로스 레일 감지 센서 (높이) | F100: =VLOOKUP(D100,Parts!D:N, 11,FALSE) -> 10519144 | G100: 파손으로 교체 | H100: =TODAY()-표1[[#This Row],[Date]] -> 122 | I100: NEW
A101: 46027 | C101: Power Supply | D101: POWER SUPPLY UNIT, DP500 24Vkw/20A IP65... | E101: DP500 IP/3-24(24V 파워서플라이) | F101: =VLOOKUP(D101,Parts!D:N, 11,FALSE) -> 10680637 | G101: A.TK01.02.027SF-TB01 파워서플라이 고장으로 교체 | H101: =TODAY()-표1[[#This Row],[Date]] -> 126 | I101: NEW
A102: 46024 | B102: 35 | C102: Retainer | D102: RETAINER SPKT=5 retainer length 130mm... | E102: 리테이너 모터 Set(Front Left, Rear Right) | F102: =VLOOKUP(D102,Parts!D:N, 11,FALSE) -> 10395046_02_0003 | G102: Front Left에서 2번째 위치 Retainer motor 동작 이상으로 교체 | H102: =TODAY()-표1[[#This Row],[Date]] -> 129 | I102: NEW
A103: 46024 | B103: 76 | C103: Sensor | D103: INDUCTIVE SENSOR, SICK IMA18-20NE1ZC0K | E103: Lifting height sensor(리프팅 높이 센서) 셔틀 하부 크로스 레일 감지 센서 (높이) | F103: =VLOOKUP(D103,Parts!D:N, 11,FALSE) -> 10519144 | G103: 파손으로 교체 | H103: =TODAY()-표1[[#This Row],[Date]] -> 129 | I103: NEW
A104: 46024 | B104: 39 | C104: Coupling | D104: SHAFT COUPLING ROTEX GS12 COMPACT | E104: VARIO 동력 축 연결 커플링 | F104: =VLOOKUP(D104,Parts!D:N, 11,FALSE) -> 10537096_01 | G104: 볼트파손으로 교체 | H104: =TODAY()-표1[[#This Row],[Date]] -> 129 | I104: NEW
A105: 46021 | B105: 35 | C105: Sensor | D105: INDUCTIVE SENSOR, I1BH027, 4MM, NFLU,... | E105: 텔레스코프 센서 | F105: =VLOOKUP(D105,Parts!D:N, 11,FALSE) -> 10623269 | G105: Front Left 센서 감지 이상으로 교체 | H105: =TODAY()-표1[[#This Row],[Date]] -> 132 | I105: NEW
A106: 46001 | B106: 15 | C106: Circuit Breaker | D106: AUTOMATIC CIRCUIT BREAKER DC, S201DC-... | E106: S201UDC Z10A / Shuttle 차단기 | F106: =VLOOKUP(D106,Parts!D:N, 11,FALSE) -> 10221867 | G106: 15/60번 셔틀 충돌로 파손되어 교체 | H106: =TODAY()-표1[[#This Row],[Date]] -> 152 | I106: NEW
A107: 46001 | B107: 60 | C107: Sideguide wheel | D107: SIDE GUIDE V8 EBG -M, OSR_EVO (Front left side, Rear right side) | E107: 2EA | F107: =VLOOKUP(D107,Parts!D:N, 11,FALSE) -> 10907771_02 | G107: 15/60번 셔틀 충돌로 Front right 파손, 4EA 교체 | H107: =TODAY()-표1[[#This Row],[Date]] -> 152 | I107: NEW
A108: 46001 | B108: 60 | C108: Sideguide wheel | D108: SIDE GUIDE V8 EBG -M, OSR_EVO (Front right side, Rear left side) | E108: 2EA | F108: =VLOOKUP(D108,Parts!D:N, 11,FALSE) -> 10907771_03 | G108: 15/60번 셔틀 충돌로 Front right 파손, 4EA 교체 | H108: =TODAY()-표1[[#This Row],[Date]] -> 152 | I108: NEW
A109: 46001 | B109: 60 | C109: Sensor | D109: INDUCTIVE SENSOR, I18H022 20MM M18 | E109: Intersection sensor(교차로 영역 센서) | F109: =VLOOKUP(D109,Parts!D:N, 11,FALSE) -> 10409303 | G109: 15/60번 셔틀 충돌로 파손되어 교체 | H109: =TODAY()-표1[[#This Row],[Date]] -> 152 | I109: NEW
A110: 45996 | B110: 42 | C110: Wheel | D110: BOGIE WHEEL, LFW ABLF EBG OSR_EVO | E110: 종방향 주행 휠 | F110: =VLOOKUP(D110,Parts!D:N, 11,FALSE) -> 10567315_01 | G110: 마모로 4ea 교체 | H110: =TODAY()-표1[[#This Row],[Date]] -> 157 | I110: NEW
A111: 45996 | B111: 42 | C111: Wheel | D111: BOGIE WHEEL, QFW ABLF EBG, OSR_EVO | E111: 횡방향 주행 휠 | F111: =VLOOKUP(D111,Parts!D:N, 11,FALSE) -> 10567316_01 | G111: 마모로 4ea 교체 | H111: =TODAY()-표1[[#This Row],[Date]] -> 157 | I111: NEW
A112: 45989 | B112: 73 | C112: Sensor | D112: OPTICAL SENSOR, OYKS950 REFL.LS M. HGA Replacement for 10409305 | E112: 교차로 중앙 센서/종방향 이동 마커 센서 | F112: =VLOOKUP(D112,Parts!D:N, 11,FALSE) -> 10867661 | G112: EVOS-0045 Error | H112: =TODAY()-표1[[#This Row],[Date]] -> 164 | I112: NEW
A113: 45975 | B113: 39 | C113: Wheel | D113: BOGIE WHEEL, QFW ABLF EBG, OSR_EVO | E113: 횡방향 주행 휠 | F113: =VLOOKUP(D113,Parts!D:N, 11,FALSE) -> 10567316_01 | G113: 마모로 4ea 교체 | H113: =TODAY()-표1[[#This Row],[Date]] -> 178 | I113: NEW
... A115: 45974 | B115: 42 | C115: Sideguide wheel | D115: SIDE GUIDE V8 EBG -M, OSR_EVO (Front right side, Rear left side) | E115: 2EA | F115: =VLOOKUP(D115,Parts!D:N, 11,FALSE) -> 10907771_03 | G115: 파손으로 4EA 교체 | H115: =TODAY()-표1[[#This Row],[Date]] -> 179 | I115: NEW
A116: 45972 | B116: 45 | C116: SEM | D116: SUPERCAPACITOR EBG V2 -M, OSR_EVO | F116: =VLOOKUP(D116,Parts!D:N, 11,FALSE) -> 10547019_03 | G116: EVOS-0045 Error | H116: =TODAY()-표1[[#This Row],[Date]] -> 181 | I116: NEW
A117: 45962 | B117: 90 | C117: Current collector(랙통로) | D117: CURRENT COLLECTOR PAIR 1 Set | E117: 종방향 | F117: =VLOOKUP(D117,Parts!D:N, 11,FALSE) -> 1 | G117: Current Collector Inspection, Pair 교체(인원엔지니어링) | H117: =TODAY()-표1[[#This Row],[Date]] -> 191 | I117: NEW
A118: 45962 | B118: 89 | C118: Current collector(랙통로) | D118: CURRENT COLLECTOR PAIR 1 Set | E118: 종방향 | F118: =VLOOKUP(D118,Parts!D:N, 11,FALSE) -> 1 | G118: Current Collector Inspection, Pair 교체(인원엔지니어링) | H118: =TODAY()-표1[[#This Row],[Date]] -> 191 | I118: NEW
A119: 45962 | B119: 88 | C119: Current collector(랙통로) | D119: CURRENT COLLECTOR PAIR 1 Set | E119: 종방향 | F119: =VLOOKUP(D119,Parts!D:N, 11,FALSE) -> 1 | G119: Current Collector Inspection, Pair 교체(인원엔지니어링) | H119: =TODAY()-표1[[#This Row],[Date]] -> 191 | I119: NEW
A120: 45962 | B120: 87 | C120: Current collector(랙통로) | D120: CURRENT COLLECTOR PAIR 1 Set | E120: 종방향 | F120: =VLOOKUP(D120,Parts!D:N, 11,FALSE) -> 1 | G120: Current Collector Inspection, Pair 교체(인원엔지니어링) | H120: =TODAY()-표1[[#This Row],[Date]] -> 191 | I120: NEW
A121: 45962 | B121: 86 | C121: Current collector(랙통로) | D121: CURRENT COLLECTOR PAIR 1 Set | E121: 종방향 | F121: =VLOOKUP(D121,Parts!D:N, 11,FALSE) -> 1 | G121: Current Collector Inspection, Pair 교체(인원엔지니어링) | H121: =TODAY()-표1[[#This Row],[Date]] -> 191 | I121: NEW
A122: 45962 | B122: 85 | C122: Current collector(크로스) | D122: CURRENT COLLECTOR PAIR 1 Set | E122: 횡방향 | F122: =VLOOKUP(D122,Parts!D:N, 11,FALSE) -> 1 | G122: Current Collector Inspection, Pair 교체(인원엔지니어링) | H122: =TODAY()-표1[[#This Row],[Date]] -> 191 | I122: NEW
A123: 45962 | B123: 84 | C123: Current collector(랙통로) | D123: CURRENT COLLECTOR PAIR 1 Set | E123: 종방향 | F123: =VLOOKUP(D123,Parts!D:N, 11,FALSE) -> 1 | G123: Current Collector Inspection, Pair 교체(인원엔지니어링) | H123: =TODAY()-표1[[#This Row],[Date]] -> 191 | I123: NEW
A124: 45962 | B124: 83 | C124: Current collector(크로스) | D124: CURRENT COLLECTOR PAIR 1 Set | E124: 횡방향 | F124: =VLOOKUP(D124,Parts!D:N, 11,FALSE) -> 1 | G124: Current Collector Inspection, Pair 교체(인원엔지니어링) | H124: =TODAY()-표1[[#This Row],[Date]] -> 191 | I124: NEW
A125: 45962 | B125: 83 | C125: Current collector(랙통로) | D125: CURRENT COLLECTOR PAIR 1 Set | E125: 종방향 | F125: =VLOOKUP(D125,Parts!D:N, 11,FALSE) -> 1 | G125: Current Collector Inspection, Pair 교체(인원엔지니어링) | H125: =TODAY()-표1[[#This Row],[Date]] -> 191 | I125: NEW
A126: 45962 | B126: 82 | C126: Current collector(랙통로) | D126: CURRENT COLLECTOR PAIR 1 Set | E126: 종방향 | F126: =VLOOKUP(D126,Parts!D:N, 11,FALSE) -> 1 | G126: Current Collector Inspection, Pair 교체(인원엔지니어링) | H126: =TODAY()-표1[[#This Row],[Date]] -> 191 | I126: NEW
A127: 45962 | B127: 80 | C127: Current collector(크로스) | D127: CURRENT COLLECTOR PAIR 1 Set | E127: 횡방향 | F127: =VLOOKUP(D127,Parts!D:N, 11,FALSE) -> 1 | G127: Current Collector Inspection, Pair 교체(인원엔지니어링) | H127: =TODAY()-표1[[#This Row],[Date]] -> 191 | I127: NEW
A128: 45962 | B128: 80 | C128: Current collector(랙통로) | D128: CURRENT COLLECTOR PAIR 1 Set | E128: 종방향 | F128: =VLOOKUP(D128,Parts!D:N, 11,FALSE) -> 1 | G128: Current Collector Inspection, Pair 교체(인원엔지니어링) | H128: =TODAY()-표1[[#This Row],[Date]] -> 191 | I128: NEW
... A178: 45959 | B178: 54 | C178: Sensor | D178: OPTICAL SENSOR, OYKS950 REFL.LS M. HGA Replacement for 10409305 | E178: 교차로 중앙 센서/종방향 이동 마커 센서 | F178: =VLOOKUP(D178,Parts!D:N, 11,FALSE) -> 10867661 | G178: 종방향 주행중 EVOS-0045 에러 발생하여 교체 | H178: =TODAY()-표1[[#This Row],[Date]] -> 194 | I178: NEW
A179: 45957 | C179: RFID | D179: MOUNTING KIT RAL1016 RFID R_KG -M, OS… | E179: HB-B 4층 3통로 3섹터 C03 | F179: =VLOOKUP(D179,Parts!D:N, 11,FALSE) -> 10428896_01_0002 | G179: 파손으로 인한 교체 | H179: =TODAY()-표1[[#This Row],[Date]] -> 196 | I179: NEW
A180: 45954 | B180: 39 | C180: Sensor | D180: OPTICAL SENSOR, OYKS950 REFL.LS M. HGA Replacement for 10409305 | E180: 교차로 중앙 센서/종방향 이동 마커 센서 | F180: =VLOOKUP(D180,Parts!D:N, 11,FALSE) -> 10867661 | G180: EVOS-0045 Error | H180: =TODAY()-표1[[#This Row],[Date]] -> 199 | I180: NEW
A181: 45953 | B181: 61 | C181: Current collector(랙통로) | D181: CURRENT COLLECTOR PAIR 1 Set | E181: 종방향 | F181: =VLOOKUP(D181,Parts!D:N, 11,FALSE) -> 1 | G181: 파손,교체 | H181: =TODAY()-표1[[#This Row],[Date]] -> 200 | I181: NEW
A182: 45953 | B182: 23 | C182: Current collector(크로스) | D182: CURRENT COLLECTOR PAIR 1 Set | E182: 횡방향 | F182: =VLOOKUP(D182,Parts!D:N, 11,FALSE) -> 1 | G182: PM(마모), Pair 교체(인원엔지니어링) | H182: =TODAY()-표1[[#This Row],[Date]] -> 200 | I182: NEW
A183: 45953 | B183: 95 | C183: Sideguide wheel | D183: SIDE GUIDE V8 EBG -M, OSR_EVO (Front right side, Rear left side) | E183: Front Right 1EA | F183: =VLOOKUP(D183,Parts!D:N, 11,FALSE) -> 10907771_03 | G183: 파손,교체 | H183: =TODAY()-표1[[#This Row],[Date]] -> 200 | I183: NEW
...

Sheet 임시) DLS PM 대여 항목
A1: 반출 날짜 | E1: Part # | F1: 수량 | G1: 반납
A2: 46087 | B2: Motor-Prot. Circuit Breaker-400V-2.5A… | C2: GV2ME08 | D2: ASRS | E2: 10217147 | F2: 1 | G2: X
A3: 46087 | B3: POWER SUPPLY UNIT, PRO MAX 480W 48V 20A | C3: 480W, 48V 파워서플라이 | D3: ASRS | E3: 10623481 | F3: 1 | G3: O
A4: 46090 | B4: POWER SUPPLY UNIT, PRO MAX 480W 48V 20A | C4: GV2ME08 | D4: ASRS | E4: 10217147 | F4: 1 | G4: X
A5: 46090 | B5: Motor-Prot. Circuit Breaker-400V-2.5A… | C5: 480W, 48V 파워서플라이 | D5: ASRS | E5: 10623481 | F5: 1 | G5: X
A6: 46114 | C6: 리프트 휠 12EA (종류 및 No. 확인 필요) | F6: 12 | H6: 정지용님

Sheet Monthly
A1: Month | B1: Category | C1: TotalQty | D1: FulfilledQty | E1: NotFulfilledQty | F1: FulfillmentRate
A2: 45959 | B2: ASRS | C2: 332 | D2: =C2-E2 -> 294 | E2: 38 | F2: =IF(C2>0,D2/C2,0) -> 0.88554217
A3: 45959 | B3: Conveyor | C3: 637 | D3: =C3-E3 -> 471 | E3: 166 | F3: =IF(C3>0,D3/C3,0) -> 0.73940345
A4: 45959 | B4: Utility | C4: 179 | D4: =C4-E4 -> 179 | E4: 0 | F4: =IF(C4>0,D4/C4,0) -> 1
A5: 45959 | B5: Electrical | C5: 71 | D5: =C5-E5 -> 71 | E5: 0 | F5: =IF(C5>0,D5/C5,0) -> 1
A6: 45991 | B6: ASRS | C6: 332 | D6: =C6-E6 -> 294 | E6: 38 | F6: =IF(C6>0,D6/C6,0) -> 0.88554217
A7: 45991 | B7: Conveyor | C7: 668 | D7: =C7-E7 -> 560 | E7: 108 | F7: =IF(C7>0,D7/C7,0) -> 0.83832335
A8: 45991 | B8: Utility | C8: 179 | D8: =C8-E8 -> 179 | E8: 0 | F8: =IF(C8>0,D8/C8,0) -> 1
A9: 45991 | B9: Electrical | C9: 71 | D9: =C9-E9 -> 71 | E9: 0 | F9: =IF(C9>0,D9/C9,0) -> 1
A10: 45992 | B10: ASRS | C10: 344 | D10: =C10-E10 -> 312 | E10: 32 | F10: =IF(C10>0,D10/C10,0) -> 0.90697674
A11: 45992 | B11: Conveyor | C11: 671 | D11: =C11-E11 -> 611 | E11: 60 | F11: =IF(C11>0,D11/C11,0) -> 0.91058122
A12: 45992 | B12: Utility | C12: 192 | D12: =C12-E12 -> 189 | E12: 3 | F12: =IF(C12>0,D12/C12,0) -> 0.984375
A13: 45992 | B13: Electrical | C13: 71 | D13: =C13-E13 -> 71 | E13: 0 | F13: =IF(C13>0,D13/C13,0) -> 1
... A25: 46082 | B25: Electrical | C25: 71 | D25: =C25-E25 -> 71 | E25: 0 | F25: =IF(C25>0,D25/C25,0) -> 1
A26: 46113 | B26: ASRS | D26: =C26-E26 -> 0 | F26: =IF(C26>0,D26/C26,0) -> 0
A27: 46113 | B27: Conveyor | D27: =C27-E27 -> 0 | F27: =IF(C27>0,D27/C27,0) -> 0
A28: 46113 | B28: Utility | D28: =C28-E28 -> 0 | F28: =IF(C28>0,D28/C28,0) -> 0
A29: 46113 | B29: Electrical | D29: =C29-E29 -> 0 | F29: =IF(C29>0,D29/C29,0) -> 0
A30: 46143 | B30: ASRS | D30: =C30-E30 -> 0
A31: 46143 | B31: Conveyor | D31: =C31-E31 -> 0
A32: 46143 | B32: Utility | D32: =C32-E32 -> 0
A33: 46143 | B33: Electrical | D33: =C33-E33 -> 0

Sheet 대응자료
G1: 1717
B2: 구분 | C2: PO amount | D2: Part Name(1) | E2: Order number | F2: Unit price (EUR) | G2: Unit price (KRW) | H2: Purchase date (Receive date) | I2: Purchase Q'ty | J2: Used Q'ty (~2024.12) | K2: Balance Q'ty (~2024.12) | L2: 잔존 금액 | M2: Used Q'ty (2023.08 ~ Current) | N2: Balance Q'ty (Current) | O2: 잔존금액 | P2: Remark
B3: 납품확인서_NIKE(KR00022)_KNAPP Spare parts 5종 | C3: 29100000 | D3: GEAR MOTOR ELR 220kw/10kw/3500 48V BL70S-... | E3: 10411034_01 | F3: 572.63 | G3: =F3*$G$1 -> 983205.71 | H3: 2023.11.24 | I3: 6 | J3: =COUNTIF('ASRS parts replacement'!F417:F10013,대응자료!E3) -> 8 | K3: =I3-J3 -> -2 | L3: 0 | M3: =COUNTIF('ASRS parts replacement'!F:F,대응자료!E3) -> 15 | N3: =VLOOKUP(D3,Parts!D:H,5,FALSE) -> 9 | O3: =N3*G3 -> 8848851.4 | P3: 안전재고 보유 사유
D4: LIFT DRIVE UNIT E60H4+EMT245 ELR 48VDC | E4: 10411039_01 | F4: 691.97 | G4: =F4*$G$1 -> 1188112.5 | I4: 6 | J4: =COUNTIF('ASRS parts replacement'!F418:F10014,대응자료!E4) -> 5 | K4: =I4-J4 -> 1 | L4: =G4*K4 -> 1188112.5 | M4: =COUNTIF('ASRS parts replacement'!F:F,대응자료!E4) -> 9 | N4: =VLOOKUP(D4,Parts!D:H,5,FALSE) -> 7 | O4: =N4*G4 -> 8316787.4 | P4: Vendor로부터 구매하여 장기 리드타임 부품(약 3개월)
D5: CURRENT COLLECTOR, 0815 2P1PH 35A REV... | E5: 10764610_01 | F5: 170.83 | G5: =F5*$G$1 -> 293315.11 | I5: 30 | J5: =COUNTIF('ASRS parts replacement'!F419:F10015,대응자료!E5) -> 235 | K5: =I5-J5 -> -205 | L5: 0 | M5: =COUNTIF('ASRS parts replacement'!F:F,대응자료!E5) -> 304 | N5: =VLOOKUP(D5,Parts!D:H,5,FALSE) -> 104 | O5: =N5*G5 -> 30504771 | P5: 고장 시 즉각 교체 안되면 다운타임 리스크 있음
D6: BOGIE WHEEL, LFW ABLF EBG OSR_EVO | E6: 10567315_01 | F6: 64.6 | G6: =F6*$G$1 -> 110918.2 | I6: 20 | J6: =COUNTIF('ASRS parts replacement'!F420:F10016,대응자료!E6) -> 3 | K6: =I6-J6 -> 17 | L6: =G6*K6 -> 1885609.4 | M6: =COUNTIF('ASRS parts replacement'!F:F,대응자료!E6) -> 20 | N6: =VLOOKUP(D6,Parts!D:H,5,FALSE) -> 61 | O6: =N6*G6 -> 6766010.2 | P6: 운영 안정성 유지를 위한 관리 대상 재고
D7: BOGIE WHEEL, QFW ABLF EBG, OSR_EVO | E7: 10567316_01 | F7: 53.39 | G7: =F7*$G$1 -> 91670.63 | I7: 20 | J7: =COUNTIF('ASRS parts replacement'!F421:F10017,대응자료!E7) -> 21 | K7: =I7-J7 -> -1 | L7: 0 | M7: =COUNTIF('ASRS parts replacement'!F:F,대응자료!E7) -> 45 | N7: =VLOOKUP(D7,Parts!D:H,5,FALSE) -> 146 | O7: =N7*G7 -> 13383912 | P7: 現 안전재고 로직: 전년도 월 평균 사용량 * 6(주문개월수) * 2(2대분), Defualt:1ea/2ea
B8: 납품확인서_KNAPP Spare parts 10종 구입 件 | C8: 42000000 | D8: CORNER ELEMENT EBG -M, OSR_EVO (rear left side) | E8: 10412613_02 | F8: 111.28 | G8: =F8*$G$1 -> 191067.76 | H8: 2023.12.14 | I8: 2 | J8: =COUNTIF('ASRS parts replacement'!F407:F10003,대응자료!E8) -> 0 | K8: =I8-J8 -> 2 | L8: =G8*K8 -> 382135.52 | M8: =COUNTIF('ASRS parts replacement'!F:F,대응자료!E8) -> 1 | N8: =VLOOKUP(D8,Parts!D:H,5,FALSE) -> 5 | O8: =N8*G8 -> 955338.8
D9: CORNER ELEMENT EBG -M, OSR_EVO (rear right side) | E9: 10412613_03 | F9: 110.4 | G9: =F9*$G$1 -> 189556.8 | I9: 3 | J9: =COUNTIF('ASRS parts replacement'!F408:F10004,대응자료!E9) -> 0 | K9: =I9-J9 -> 3 | L9: =G9*K9 -> 568670.4 | M9: =COUNTIF('ASRS parts replacement'!F:F,대응자료!E9) -> 3 | N9: =VLOOKUP(D9,Parts!D:H,5,FALSE) -> 7 | O9: =N9*G9 -> 1326897.6
D10: CORNER ELEMENT EBG -M, OSR_EVO (front right side) | E10: 10412613_04 | F10: 111.28 | G10: =F10*$G$1 -> 191067.76 | I10: 2 | J10: =COUNTIF('ASRS parts replacement'!F409:F10005,대응자료!E10) -> 0 | K10: =I10-J10 -> 2 | L10: =G10*K10 -> 382135.52 | M10: =COUNTIF('ASRS parts replacement'!F:F,대응자료!E10) -> 1 | N10: =VLOOKUP(D10,Parts!D:H,5,FALSE) -> 7 | O10: =N10*G10 -> 1337474.3
D11: CORNER ELEMENT EBG -M, OSR_EVO (front left side) | E11: 10412613_05 | F11: 114.52 | G11: =F11*$G$1 -> 196630.84 | I11: 2 | J11: =COUNTIF('ASRS parts replacement'!F410:F10006,대응자료!E11) -> 0 | K11: =I11-J11 -> 2 | L11: =G11*K11 -> 393261.68 | M11: =COUNTIF('ASRS parts replacement'!F:F,대응자료!E11) -> 0 | N11: =VLOOKUP(D11,Parts!D:H,5,FALSE) -> 6 | O11: =N11*G11 -> 1179785
D12: GEAR MOTOR ELR 350kw/7.5kw/3150 24V BL70M... | E12: 10410230_01 | F12: 668.55 | G12: =F12*$G$1 -> 1147900.3 | I12: 3 | J12: =COUNTIF('ASRS parts replacement'!F411:F10007,대응자료!E12) -> 1 | K12: =I12-J12 -> 2 | L12: =G12*K12 -> 2295800.7 | M12: =COUNTIF('ASRS parts replacement'!F:F,대응자료!E12) -> 1 | N12: =VLOOKUP(D12,Parts!D:H,5,FALSE) -> 7 | O12: =N12*G12 -> 8035302.4
D13: GEAR MOTOR ELRkw/11.8 48V BL57AL-48V + ... | E13: 10395200_01 | F13: 458.11 | G13: =F13*$G$1 -> 786574.87 | I13: 3 | J13: =COUNTIF('ASRS parts replacement'!F412:F10008,대응자료!E13) -> 0 | K13: =I13-J13 -> 3 | L13: =G13*K13 -> 2359724.6 | M13: =COUNTIF('ASRS parts replacement'!F:F,대응자료!E13) -> 0 | N13: =VLOOKUP(D13,Parts!D:H,5,FALSE) -> 9 | O13: =N13*G13 -> 7079173.8
D14: GEAR MOTOR ELRkw/33kw/3000 48V BL42YS-48V... | E14: 10540023_01 | F14: 555.82 | G14: =F14*$G$1 -> 954342.94 | I14: 3 | J14: =COUNTIF('ASRS parts replacement'!F413:F10009,대응자료!E14) -> 1 | K14: =I14-J14 -> 2 | L14: =G14*K14 -> 1908685.9 | M14: =COUNTIF('ASRS parts replacement'!F:F,대응자료!E14) -> 2 | N14: =VLOOKUP(D14,Parts!D:H,5,FALSE) -> 8 | O14: =N14*G14 -> 7634743.5
D15: SHAFT COUPLING ROTEX GS12 COMPACT | E15: 10537096_01 | F15: 25.99 | G15: =F15*$G$1 -> 44624.83 | I15: 30 | J15: =COUNTIF('ASRS parts replacement'!F414:F10010,대응자료!E15) -> 0 | K15: =I15-J15 -> 30 | L15: =G15*K15 -> 1338744.9 | M15: =COUNTIF('ASRS parts replacement'!F:F,대응자료!E15) -> 1 | N15: =VLOOKUP(D15,Parts!D:H,5,FALSE) -> 28 | O15: =N15*G15 -> 1249495.2
D16: ASSEMB. PRINTED CIRCUIT BOARD, SHUTTL... Replacement for 10676955_02 | E16: 10676955_08 | F16: 1059.9 | G16: =F16*$G$1 -> 1819848.3 | I16: 5 | J16: =COUNTIF('ASRS parts replacement'!F415:F10011,대응자료!E16) -> 2 | K16: =I16-J16 -> 3 | L16: =G16*K16 -> 5459544.9 | M16: =COUNTIF('ASRS parts replacement'!F:F,대응자료!E16) -> 4 | N16: =VLOOKUP(D16,Parts!D:H,5,FALSE) -> 6 | O16: =N16*G16 -> 10919090
D17: TABLET, KAG ZEBRA ET51 10" RW INKL. R.. | E17: 10652991_01 | F17: 3155.27 | G17: =F17*$G$1 -> 5417598.6 | I17: 2 | J17: =COUNTIF('ASRS parts replacement'!F416:F10012,대응자료!E17) -> 2 | K17: =I17-J17 -> 0 | L17: =G17*K17 -> 0 | M17: =COUNTIF('ASRS parts replacement'!F:F,대응자료!E17) -> 2 | N17: =VLOOKUP(D17,Parts!D:H,5,FALSE) -> 1 | O17: =N17*G17 -> 5417598.6
B18: 납품확인서_KNAPP Spare parts 구입 件 | C18: 8200000 | D18: ACCESS CONCEPT LZYL=4510 LINKS 1E V2 ... | E18: 10609544_02_0001 | F18: 516.15 | G18: =F18*$G$1 -> 886229.55 | H18: 2024.02.16 | I18: 5 | J18: =COUNTIF('ASRS parts replacement'!F406:F10002,대응자료!E18) -> 10 | K18: =I18-J18 -> -5 | L18: 0 | M18: =COUNTIF('ASRS parts replacement'!F:F,대응자료!E18) -> 10 | N18: =VLOOKUP(D18,Parts!D:H,5,FALSE) -> 10 | O18: =N18*G18 -> 8862295.5
B19: 납품확인서_KNAPP Spare parts 15종 구입 件 | C19: 42000000 | D19: OPTICAL SENSOR, OYKS950 REFL.LS M. HGA Replacement for 10409305 | E19: 10867661 | F19: 93 | G19: =F19*$G$1 -> 159681 | H19: 2024.02.16 | I19: 10 | J19: =COUNTIF('ASRS parts replacement'!F425:F10021,대응자료!E19) -> 10 | K19: =I19-J19 -> 0 | L19: =G19*K19 -> 0 | M19: =COUNTIF('ASRS parts replacement'!F:F,대응자료!E19) -> 26 | N19: =VLOOKUP(D19,Parts!D:H,5,FALSE) -> 88 | O19: =N19*G19 -> 14051928
D20: INDUCTIVE SENSOR, I18H022 20MM M18 | E20: 10409303 | F20: 51.66 | G20: =F20*$G$1 -> 88700.22 | I20: 10 | J20: =COUNTIF('ASRS parts replacement'!F426:F10022,대응자료!E20) -> 2 | K20: =I20-J20 -> 8 | L20: =G20*K20 -> 709601.76 | M20: =COUNTIF('ASRS parts replacement'!F:F,대응자료!E20) -> 8 | N20: =VLOOKUP(D20,Parts!D:H,5,FALSE) -> 10 | O20: =N20*G20 -> 887002.2
D21: INDUCTIVE SENSOR, SICK IMA18-20NE1ZC0K | E21: 10519144 | F21: 289.48 | G21: =F21*$G$1 -> 497037.16 | I21: 10 | J21: =COUNTIF('ASRS parts replacement'!F427:F10023,대응자료!E21) -> 1 | K21: =I21-J21 -> 9 | L21: =G21*K21 -> 4473334.4 | M21: =COUNTIF('ASRS parts replacement'!F:F,대응자료!E21) -> 3 | N21: =VLOOKUP(D21,Parts!D:H,5,FALSE) -> 16 | O21: =N21*G21 -> 7952594.6
D22: HEX.NUT, EN1661 M6-8-ZP-SPERR | E22: 10200757 | F22: 0.2 | G22: =F22*$G$1 -> 343.4 | H22: 2024.02.29 | I22: 100 | J22: =COUNTIF('ASRS parts replacement'!F428:F10024,대응자료!E22) -> 0 | K22: =I22-J22 -> 100 | L22: =G22*K22 -> 34340 | M22: =COUNTIF('ASRS parts replacement'!F:F,대응자료!E22) -> 0 | N22: 100 | O22: =N22*G22 -> 34340
D23: POWER SUPPLY UNIT, TDR-960-24V 40A | E23: 10446264 | F23: 255.47 | G23: =F23*$G$1 -> 438641.99 | I23: 3 | J23: =COUNTIF('ASRS parts replacement'!F429:F10025,대응자료!E23) -> 0 | K23: =I23-J23 -> 3 | L23: =G23*K23 -> 1315926 | M23: =COUNTIF('ASRS parts replacement'!F:F,대응자료!E23) -> 1 | N23: =VLOOKUP(D23,Parts!D:H,5,FALSE) -> 3 | O23: =N23*G23 -> 1315926
D24: POWER SUPPLY UNIT, TDR-960-48V 20A | E24: 10218312 | F24: 255.47 | G24: =F24*$G$1 -> 438641.99 | I24: 3 | J24: =COUNTIF('ASRS parts replacement'!F430:F10026,대응자료!E24) -> 0 | K24: =I24-J24 -> 3 | L24: =G24*K24 -> 1315926 | M24: =COUNTIF('ASRS parts replacement'!F:F,대응자료!E24) -> 0 | N24: =VLOOKUP(D24,Parts!D:H,5,FALSE) -> 4 | O24: =N24*G24 -> 1754568
D25: ACCESS CONCEPT LZYL=4510 LINKS 1E V2 ... | E25: 10609544_02_0001 | F25: 516.15 | G25: =F25*$G$1 -> 886229.55 | I25: 3 | J25: =COUNTIF('ASRS parts replacement'!F431:F10027,대응자료!E25) -> 8 | K25: =I25-J25 -> -5 | L25: 0 | M25: =COUNTIF('ASRS parts replacement'!F:F,대응자료!E25) -> 10 | N25: =VLOOKUP(D25,Parts!D:H,5,FALSE) -> 10 | O25: =N25*G25 -> 8862295.5
D26: ACCESS CONCEPT EMERGENCY E -KPL, K_LOCK | E26: 10505322_01 | F26: 405.55 | G26: =F26*$G$1 -> 696329.35 | I26: 2 | J26: =COUNTIF('ASRS parts replacement'!F432:F10028,대응자료!E26) -> 0 | K26: =I26-J26 -> 2 | L26: =G26*K26 -> 1392658.7 | M26: =COUNTIF('ASRS parts replacement'!F:F,대응자료!E26) -> 0 | N26: =VLOOKUP(D26,Parts!D:H,5,FALSE) -> 5 | O26: =N26*G26 -> 3481646.8
D27: CHAIN TELL1490 TEL. -M, OSR_EVO | E27: 10395761_01_0016 | F27: 150.43 | G27: =F27*$G$1 -> 258288.31 | I27: 5 | J27: =COUNTIF('ASRS parts replacement'!F433:F10029,대응자료!E27) -> 0 | K27: =I27-J27 -> 5 | L27: =G27*K27 -> 1291441.6 | M27: =COUNTIF('ASRS parts replacement'!F:F,대응자료!E27) -> 0 | N27: =VLOOKUP(D27,Parts!D:H,5,FALSE) -> 12 | O27: =N27*G27 -> 3099459.7
D28: Door safety switch, PILZ 506334 (506301+506308) | E28: 10217650 | F28: 121.08 | G28: =F28*$G$1 -> 207894.36 | I28: 10 | J28: =COUNTIF('ASRS parts replacement'!F434:F10030,대응자료!E28) -> 1 | K28: =I28-J28 -> 9 | L28: =G28*K28 -> 1871049.2 | M28: =COUNTIF('ASRS parts replacement'!F:F,대응자료!E28) -> 3 | N28: =VLOOKUP(D28,Parts!D:H,5,FALSE) -> 12 | O28: =N28*G28 -> 2494732.3
D29: CURRENT COLLECTOR, 0815 2P1PH 35A REV... | E29: 10764610_01 | F29: 170.83 | G29: =F29*$G$1 -> 293315.11 | I29: 30 | J29: =COUNTIF('ASRS parts replacement'!F435:F10031,대응자료!E29) -> 227 | K29: =I29-J29 -> -197 | L29: 0 | M29: =COUNTIF('ASRS parts replacement'!F:F,대응자료!E29) -> 304 | N29: =VLOOKUP(D29,Parts!D:H,5,FALSE) -> 104 | O29: =N29*G29 -> 30504771
D30: Sideguide wheel_Vibration buffer | E30: 10634710_01 | F30: 0.25 | G30: =F30*$G$1 -> 429.25 | I30: 100 | J30: =COUNTIF('ASRS parts replacement'!F436:F10032,대응자료!E30) -> 0 | K30: =I30-J30 -> 100 | L30: =G30*K30 -> 42925 | M30: =COUNTIF('ASRS parts replacement'!F:F,대응자료!E30) -> 0 | N30: =VLOOKUP(D30,Parts!D:H,5,FALSE) -> 70 | O30: =N30*G30 -> 30047.5
D31: SIDE GUIDE WHEEL, COMPENSA EBG, OSR_EVO | E31: 10679338_01 | F31: 4.12 | G31: =F31*$G$1 -> 7074.04 | I31: 100 | J31: =COUNTIF('ASRS parts replacement'!F437:F10033,대응자료!E31) -> 0 | K31: =I31-J31 -> 100 | L31: =G31*K31 -> 707404 | M31: =COUNTIF('ASRS parts replacement'!F:F,대응자료!E31) -> 0 | N31: =VLOOKUP(D31,Parts!D:H,5,FALSE) -> 100 | O31: =N31*G31 -> 707404
D32: Sideguide wheel_Bracket (Front left side, rear right side | E32: 10611156_02 | F32: 9.64 | G32: =F32*$G$1 -> 16551.88 | I32: 40 | J32: =COUNTIF('ASRS parts replacement'!F438:F10034,대응자료!E32) -> 14 | K32: =I32-J32 -> 26 | L32: =G32*K32 -> 430348.88 | M32: =COUNTIF('ASRS parts replacement'!F:F,대응자료!E32) -> 16 | N32: =VLOOKUP(D32,Parts!D:H,5,FALSE) -> 26 | O32: =N32*G32 -> 430348.88
D33: Sideguide wheel_Bracket (Front right side, Rear left side | E33: 10611156_03 | F33: 9.64 | G33: =F33*$G$1 -> 16551.88 | I33: 40 | J33: =COUNTIF('ASRS parts replacement'!F439:F10035,대응자료!E33) -> 29 | K33: =I33-J33 -> 11 | L33: =G33*K33 -> 182070.68 | M33: =COUNTIF('ASRS parts replacement'!F:F,대응자료!E33) -> 32 | N33: =VLOOKUP(D33,Parts!D:H,5,FALSE) -> 11 | O33: =N33*G33 -> 182070.68
B34: 납품확인서_KNAPP Spare parts 2종 구입 件 | C34: 2690000 | D34: INCREMENTAL ENCODER, DBS36E-BBAP00S43 | E34: 10408341 | F34: 104.2 | G34: =F34*$G$1 -> 178911.4 | H34: 2024.03.27 | I34: 4 | J34: =COUNTIF('ASRS parts replacement'!F422:F10018,대응자료!E34) -> 4 | K34: =I34-J34 -> 0 | L34: =G34*K34 -> 0 | M34: =COUNTIF('ASRS parts replacement'!F:F,대응자료!E34) -> 5 | N34: =VLOOKUP(D34,Parts!D:H,5,FALSE) -> 8 | O34: =N34*G34 -> 1431291.2
D35: STEPPER MOTOR HSY223-F06C + PX28S-16,... | E35: 10395201_01 | F35: 97.2 | G35: =F35*$G$1 -> 166892.4 | I35: 4 | J35: =COUNTIF('ASRS parts replacement'!F423:F10019,대응자료!E35) -> 5 | K35: =I35-J35 -> -1 | L35: 0 | M35: =COUNTIF('ASRS parts replacement'!F:F,대응자료!E35) -> 5 | N35: =VLOOKUP(D35,Parts!D:H,5,FALSE) -> 19 | O35: =N35*G35 -> 3170955.6
B36: 납품확인서_KNAPP Spare parts 1종 구입 件 | C36: 1680000 | D36: RFID READER, IQT1-FP-R4-V1 | E36: 10404892 | F36: 258.19 | G36: =F36*$G$1 -> 443312.23 | H36: 2024.04.25 | I36: 2 | J36: =COUNTIF('ASRS parts replacement'!F424:F10020,대응자료!E36) -> 8 | K36: =I36-J36 -> -6 | L36: 0 | M36: =COUNTIF('ASRS parts replacement'!F:F,대응자료!E36) -> 12 | N36: =VLOOKUP(D36,Parts!D:H,5,FALSE) -> 4 | O36: =N36*G36 -> 1773248.9
L37: =SUM(L3:L36) -> 31929452 | O37: =SUM(O3:O36) -> 2.0398216e+08

Sheet Sheet1
N1: 1712
B2: 구분 | C2: Part Name(1) | D2: Order number | E2: 설치설비 | F2: 설치갯수 | G2: 현재재고 | H2: 안전재고 | I2: 안전재고 충족현황 | J2: 보관 위치 | K2: Supplier | L2: 제조사 | M2: Unit price (EUR) | N2: Unit price (KRW) | O2: Purchase date (Receive date) | P2: Purchase Q'ty | Q2: Used Q'ty (2023.08~)
B3: 납품확인서_KNAPP Spare parts 구입 件 | C3: ACCESS CONCEPT LZYL=4510 LINKS 1E V2 ... | D3: 10609544_02_0001 | E3: OSR Rack | F3: 94 | G3: 10 | H3: =_xlfn.LET( _xlpm.orderNum,#REF!, _xlpm.usedCount, COUNTIFS( 'ASRS parts replacement'!F:F, _xlpm.orderNum, 'ASRS parts replacement'!A:A, ">=2025-01-01", 'ASRS parts replacement'!A:A, "<=2025-12-31"), IF(_xlpm.usedCount=0, 2, MAX(2, _xlpm.usedCount/12*6*2)) ) -> 2 | I3: =IF(G3<H3,"X","O") -> O | J3: 124 | M3: 516.15 | N3: =M3*$N$1 -> 883648.8 | O3: 2024.02.16 | P3: 5 | Q3: =COUNTIF('ASRS parts replacement'!F:F,D3) -> 10
B4: 납품확인서_KNAPP Spare parts 10종 구입 件 | C4: CORNER ELEMENT EBG -M, OSR_EVO (rear left side) | D4: 10412613_02 | E4: OSR Shuttle | F4: 90 | G4: 5 | H4: =_xlfn.LET( _xlpm.orderNum,#REF!, _xlpm.usedCount, COUNTIFS( 'ASRS parts replacement'!F:F, _xlpm.orderNum, 'ASRS parts replacement'!A:A, ">=2025-01-01", 'ASRS parts replacement'!A:A, "<=2025-12-31"), IF(_xlpm.usedCount=0, 2, MAX(2, _xlpm.usedCount/12*6*2)) ) -> 2 | I4: =IF(G4<H4,"X","O") -> O | J4: 205 | K4: KNAPP | M4: 111.28 | N4: =M4*$N$1 -> 190511.36 | O4: 2023.12.14 | P4: 2 | Q4: =COUNTIF('ASRS parts replacement'!F:F,D4) -> 1
C5: CORNER ELEMENT EBG -M, OSR_EVO (rear right side) | D5: 10412613_03 | E5: OSR Shuttle | F5: 90 | G5: 7 | H5: =_xlfn.LET( _xlpm.orderNum,#REF!, _xlpm.usedCount, COUNTIFS( 'ASRS parts replacement'!F:F, _xlpm.orderNum, 'ASRS parts replacement'!A:A, ">=2025-01-01", 'ASRS parts replacement'!A:A, "<=2025-12-31"), IF(_xlpm.usedCount=0, 2, MAX(2, _xlpm.usedCount/12*6*2)) ) -> 2 | I5: =IF(G5<H5,"X","O") -> O | J5: 204 | K5: KNAPP | M5: 110.4 | N5: =M5*$N$1 -> 189004.8 | P5: 3 | Q5: =COUNTIF('ASRS parts replacement'!F:F,D5) -> 3
C6: CORNER ELEMENT EBG -M, OSR_EVO (front right side) | D6: 10412613_04 | E6: OSR Shuttle | F6: 90 | G6: 7 | H6: =_xlfn.LET( _xlpm.orderNum,#REF!, _xlpm.usedCount, COUNTIFS( 'ASRS parts replacement'!F:F, _xlpm.orderNum, 'ASRS parts replacement'!A:A, ">=2025-01-01", 'ASRS parts replacement'!A:A, "<=2025-12-31"), IF(_xlpm.usedCount=0, 2, MAX(2, _xlpm.usedCount/12*6*2)) ) -> 2 | I6: =IF(G6<H6,"X","O") -> O | J6: 205 | K6: KNAPP | M6: 111.28 | N6: =M6*$N$1 -> 190511.36 | P6: 2 | Q6: =COUNTIF('ASRS parts replacement'!F:F,D6) -> 1
C7: CORNER ELEMENT EBG -M, OSR_EVO (front left side) | D7: 10412613_05 | E7: OSR Shuttle | F7: 90 | G7: 6 | H7: =_xlfn.LET( _xlpm.orderNum,#REF!, _xlpm.usedCount, COUNTIFS( 'ASRS parts replacement'!F:F, _xlpm.orderNum, 'ASRS parts replacement'!A:A, ">=2025-01-01", 'ASRS parts replacement'!A:A, "<=2025-12-31"), IF(_xlpm.usedCount=0, 2, MAX(2, _xlpm.usedCount/12*6*2)) ) -> 2 | I7: =IF(G7<H7,"X","O") -> O | J7: 204 | K7: KNAPP | M7: 114.52 | N7: =M7*$N$1 -> 196058.24 | P7: 2 | Q7: =COUNTIF('ASRS parts replacement'!F:F,D7) -> 0
C8: GEAR MOTOR ELR 350kw/7.5kw/3150 24V BL70M... | D8: 10410230_01 | E8: OSR Shuttle | F8: 90 | G8: 7 | H8: =_xlfn.LET( _xlpm.orderNum,#REF!, _xlpm.usedCount, COUNTIFS( 'ASRS parts replacement'!F:F, _xlpm.orderNum, 'ASRS parts replacement'!A:A, ">=2025-01-01", 'ASRS parts replacement'!A:A, "<=2025-12-31"), IF(_xlpm.usedCount=0, 2, MAX(2, _xlpm.usedCount/12*6*2)) ) -> 2 | I8: =IF(G8<H8,"X","O") -> O | J8: 205 | K8: KNAPP | M8: 668.55 | N8: =M8*$N$1 -> 1144557.6 | P8: 3 | Q8: =COUNTIF('ASRS parts replacement'!F:F,D8) -> 1
C9: GEAR MOTOR ELRkw/11.8 48V BL57AL-48V + ... | D9: 10395200_01 | E9: OSR Shuttle | F9: 180 | G9: 9 | H9: =_xlfn.LET( _xlpm.orderNum,#REF!, _xlpm.usedCount, COUNTIFS( 'ASRS parts replacement'!F:F, _xlpm.orderNum, 'ASRS parts replacement'!A:A, ">=2025-01-01", 'ASRS parts replacement'!A:A, "<=2025-12-31"), IF(_xlpm.usedCount=0, 2, MAX(2, _xlpm.usedCount/12*6*2)) ) -> 2 | I9: =IF(G9<H9,"X","O") -> O | J9: 205 | K9: KNAPP | M9: 458.11 | N9: =M9*$N$1 -> 784284.32 | P9: 3 | Q9: =COUNTIF('ASRS parts replacement'!F:F,D9) -> 0
C10: GEAR MOTOR ELRkw/33kw/3000 48V BL42YS-48V... | D10: 10540023_01 | E10: OSR Shuttle | F10: 90 | G10: 8 | H10: =_xlfn.LET( _xlpm.orderNum,#REF!, _xlpm.usedCount, COUNTIFS( 'ASRS parts replacement'!F:F, _xlpm.orderNum, 'ASRS parts replacement'!A:A, ">=2025-01-01", 'ASRS parts replacement'!A:A, "<=2025-12-31"), IF(_xlpm.usedCount=0, 2, MAX(2, _xlpm.usedCount/12*6*2)) ) -> 2 | I10: =IF(G10<H10,"X","O") -> O | J10: 242 | K10: KNAPP | M10: 555.82 | N10: =M10*$N$1 -> 951563.84 | P10: 3 | Q10: =COUNTIF('ASRS parts replacement'!F:F,D10) -> 2
C11: SHAFT COUPLING ROTEX GS12 COMPACT | D11: 10537096_01 | E11: OSR Shuttle | F11: 90 | G11: 28 | H11: =_xlfn.LET( _xlpm.orderNum,#REF!, _xlpm.usedCount, COUNTIFS( 'ASRS parts replacement'!F:F, _xlpm.orderNum, 'ASRS parts replacement'!A:A, ">=2025-01-01", 'ASRS parts replacement'!A:A, "<=2025-12-31"), IF(_xlpm.usedCount=0, 2, MAX(2, _xlpm.usedCount/12*6*2)) ) -> 2 | I11: =IF(G11<H11,"X","O") -> O | J11: 242 | K11: KNAPP | M11: 25.99 | N11: =M11*$N$1 -> 44494.88 | P11: 30 | Q11: =COUNTIF('ASRS parts replacement'!F:F,D11) -> 1
C12: ASSEMB. PRINTED CIRCUIT BOARD, SHUTTL... Replacement for 10676955_02 | D12: 10676955_08 | E12: OSR Shuttle | F12: 90 | G12: 6 | H12: =_xlfn.LET( _xlpm.orderNum,#REF!, _xlpm.usedCount, COUNTIFS( 'ASRS parts replacement'!F:F, _xlpm.orderNum, 'ASRS parts replacement'!A:A, ">=2025-01-01", 'ASRS parts replacement'!A:A, "<=2025-12-31"), IF(_xlpm.usedCount=0, 2, MAX(2, _xlpm.usedCount/12*6*2)) ) -> 2 | I12: =IF(G12<H12,"X","O") -> O | J12: 123 | K12: KNAPP | M12: 1059.9 | N12: =M12*$N$1 -> 1814548.8 | P12: 5 | Q12: =COUNTIF('ASRS parts replacement'!F:F,D12) -> 4
C13: TABLET, KAG ZEBRA ET51 10" RW INKL. R.. | D13: 10652991_01 | E13: ASRS | F13: 3 | G13: 1 | H13: 1 | I13: =IF(G13<H13,"X","O") -> O | J13: 213 | K13: KNAPP | L13: Zebra | M13: 3155.27 | N13: =M13*$N$1 -> 5401822.2 | P13: 2 | Q13: =COUNTIF('ASRS parts replacement'!F:F,D13) -> 2
B14: 납품확인서_NIKE(KR00022)_KNAPP Spare parts 5종 | C14: GEAR MOTOR ELR 220kw/10kw/3500 48V BL70S-... | D14: 10411034_01 | E14: OSR Shuttle | F14: 90 | G14: 9 | H14: =_xlfn.LET( _xlpm.orderNum,#REF!, _xlpm.usedCount, COUNTIFS( 'ASRS parts replacement'!F:F, _xlpm.orderNum, 'ASRS parts replacement'!A:A, ">=2025-01-01", 'ASRS parts replacement'!A:A, "<=2025-12-31"), IF(_xlpm.usedCount=0, 2, MAX(2, _xlpm.usedCount/12*6*2)) ) -> 2 | I14: =IF(G14<H14,"X","O") -> O | J14: 203 | K14: KNAPP | M14: 572.63 | N14: =M14*$N$1 -> 980342.56 | O14: 2023.11.24 | P14: 6 | Q14: =COUNTIF('ASRS parts replacement'!F:F,D14) -> 15
C15: LIFT DRIVE UNIT E60H4+EMT245 ELR 48VDC | D15: 10411039_01 | E15: OSR Shuttle | F15: 90 | G15: 7 | H15: =_xlfn.LET( _xlpm.orderNum,#REF!, _xlpm.usedCount, COUNTIFS( 'ASRS parts replacement'!F:F, _xlpm.orderNum, 'ASRS parts replacement'!A:A, ">=2025-01-01", 'ASRS parts replacement'!A:A, "<=2025-12-31"), IF(_xlpm.usedCount=0, 2, MAX(2, _xlpm.usedCount/12*6*2)) ) -> 2 | I15: =IF(G15<H15,"X","O") -> O | J15: 205 | K15: KNAPP | M15: 691.97 | N15: =M15*$N$1 -> 1184652.6 | P15: 6 | Q15: =COUNTIF('ASRS parts replacement'!F:F,D15) -> 9
C16: CURRENT COLLECTOR, 0815 2P1PH 35A REV... | D16: 10764610_01 | E16: OSR Shuttle | F16: 180 | G16: 104 | H16: =_xlfn.LET( _xlpm.orderNum,#REF!, _xlpm.usedCount, COUNTIFS( 'ASRS parts replacement'!F:F, _xlpm.orderNum, 'ASRS parts replacement'!A:A, ">=2025-01-01", 'ASRS parts replacement'!A:A, "<=2025-12-31"), IF(_xlpm.usedCount=0, 2, MAX(2, _xlpm.usedCount/12*6*2)) ) -> 2 | I16: =IF(G16<H16,"X","O") -> O | J16: 202 | K16: KNAPP | M16: 170.83 | N16: =M16*$N$1 -> 292460.96 | P16: 30 | Q16: =COUNTIF('ASRS parts replacement'!F:F,D16) -> 304
C17: BOGIE WHEEL, LFW ABLF EBG OSR_EVO | D17: 10567315_01 | E17: OSR Shuttle | F17: 360 | G17: 61 | H17: =_xlfn.LET( _xlpm.orderNum,#REF!, _xlpm.usedCount, COUNTIFS( 'ASRS parts replacement'!F:F, _xlpm.orderNum, 'ASRS parts replacement'!A:A, ">=2025-01-01", 'ASRS parts replacement'!A:A, "<=2025-12-31"), IF(_xlpm.usedCount=0, 2, MAX(2, _xlpm.usedCount/12*6*2)) ) -> 2 | I17: =IF(G17<H17,"X","O") -> O | J17: 242 | K17: KNAPP | M17: 64.6 | N17: =M17*$N$1 -> 110595.2 | P17: 20 | Q17: =COUNTIF('ASRS parts replacement'!F:F,D17) -> 20
C18: BOGIE WHEEL, QFW ABLF EBG, OSR_EVO | D18: 10567316_01 | E18: OSR Shuttle | F18: 360 | G18: 146 | H18: =_xlfn.LET( _xlpm.orderNum,#REF!, _xlpm.usedCount, COUNTIFS( 'ASRS parts replacement'!F:F, _xlpm.orderNum, 'ASRS parts replacement'!A:A, ">=2025-01-01", 'ASRS parts replacement'!A:A, "<=2025-12-31"), IF(_xlpm.usedCount=0, 2, MAX(2, _xlpm.usedCount/12*6*2)) ) -> 2 | I18: =IF(G18<H18,"X","O") -> O | J18: 242 | K18: KNAPP | M18: 53.39 | N18: =M18*$N$1 -> 91403.68 | P18: 20 | Q18: =COUNTIF('ASRS parts replacement'!F:F,D18) -> 45
B19: 납품확인서_KNAPP Spare parts 2종 구입 件 | C19: INCREMENTAL ENCODER, DBS36E-BBAP00S43 | D19: 10408341 | E19: OSR Shuttle | F19: 180 | G19: 8 | H19: =_xlfn.LET( _xlpm.orderNum,#REF!, _xlpm.usedCount, COUNTIFS( 'ASRS parts replacement'!F:F, _xlpm.orderNum, 'ASRS parts replacement'!A:A, ">=2025-01-01", 'ASRS parts replacement'!A:A, "<=2025-12-31"), IF(_xlpm.usedCount=0, 2, MAX(2, _xlpm.usedCount/12*6*2)) ) -> 2 | I19: =IF(G19<H19,"X","O") -> O | J19: 242 | K19: KNAPP | M19: 104.2 | N19: =M19*$N$1 -> 178390.4 | O19: 2024.03.27 | P19: 4 | Q19: =COUNTIF('ASRS parts replacement'!F:F,D19) -> 5
C20: STEPPER MOTOR HSY223-F06C + PX28S-16,... | D20: 10395201_01 | E20: OSR Shuttle | F20: 720 | G20: 19 | H20: =_xlfn.LET( _xlpm.orderNum,#REF!, _xlpm.usedCount, COUNTIFS( 'ASRS parts replacement'!F:F, _xlpm.orderNum, 'ASRS parts replacement'!A:A, ">=2025-01-01", 'ASRS parts replacement'!A:A, "<=2025-12-31"), IF(_xlpm.usedCount=0, 2, MAX(2, _xlpm.usedCount/12*6*2)) ) -> 2 | I20: =IF(G20<H20,"X","O") -> O | J20: 242 | K20: KNAPP | M20: 97.2 | N20: =M20*$N$1 -> 166406.4 | P20: 4 | Q20: =COUNTIF('ASRS parts replacement'!F:F,D20) -> 5
B21: 납품확인서_KNAPP Spare parts 1종 구입 件 | C21: RFID READER, IQT1-FP-R4-V1 | D21: 10404892 | E21: OSR Shuttle | F21: 90 | G21: 4 | H21: =_xlfn.LET( _xlpm.orderNum,#REF!, _xlpm.usedCount, COUNTIFS( 'ASRS parts replacement'!F:F, _xlpm.orderNum, 'ASRS parts replacement'!A:A, ">=2025-01-01", 'ASRS parts replacement'!A:A, "<=2025-12-31"), IF(_xlpm.usedCount=0, 2, MAX(2, _xlpm.usedCount/12*6*2)) ) -> 2 | I21: =IF(G21<H21,"X","O") -> O | J21: 114 | L21: Pepperl+Fuchs | M21: 258.19 | N21: =M21*$N$1 -> 442021.28 | O21: 2024.04.25 | P21: 2 | Q21: =COUNTIF('ASRS parts replacement'!F:F,D21) -> 12
B22: 납품확인서_KNAPP Spare parts 15종 구입 件 | C22: OPTICAL SENSOR, OYKS950 REFL.LS M. HGA Replacement for 10409305 | D22: 10867661 | E22: OSR Shuttle | F22: 180 | G22: 88 | H22: =_xlfn.LET( _xlpm.orderNum,#REF!, _xlpm.usedCount, COUNTIFS( 'ASRS parts replacement'!F:F, _xlpm.orderNum, 'ASRS parts replacement'!A:A, ">=2025-01-01", 'ASRS parts replacement'!A:A, "<=2025-12-31"), IF(_xlpm.usedCount=0, 2, MAX(2, _xlpm.usedCount/12*6*2)) ) -> 2 | I22: =IF(G22<H22,"X","O") -> O | J22: 213 | L22: Wenglor | M22: 93 | N22: =M22*$N$1 -> 159216 | O22: 2024.02.16 | P22: 10 | Q22: =COUNTIF('ASRS parts replacement'!F:F,D22) -> 26
C23: INDUCTIVE SENSOR, I18H022 20MM M18 | D23: 10409303 | E23: OSR Shuttle | F23: 90 | G23: 10 | H23: =_xlfn.LET( _xlpm.orderNum,#REF!, _xlpm.usedCount, COUNTIFS( 'ASRS parts replacement'!F:F, _xlpm.orderNum, 'ASRS parts replacement'!A:A, ">=2025-01-01", 'ASRS parts replacement'!A:A, "<=2025-12-31"), IF(_xlpm.usedCount=0, 2, MAX(2, _xlpm.usedCount/12*6*2)) ) -> 2 | I23: =IF(G23<H23,"X","O") -> O | J23: 213 | L23: Wenglor | M23: 51.66 | N23: =M23*$N$1 -> 88441.92 | P23: 10 | Q23: =COUNTIF('ASRS parts replacement'!F:F,D23) -> 8
C24: INDUCTIVE SENSOR, SICK IMA18-20NE1ZC0K | D24: 10519144 | E24: OSR Shuttle | F24: 90 | G24: 16 | H24: =_xlfn.LET( _xlpm.orderNum,#REF!, _xlpm.usedCount, COUNTIFS( 'ASRS parts replacement'!F:F, _xlpm.orderNum, 'ASRS parts replacement'!A:A, ">=2025-01-01", 'ASRS parts replacement'!A:A, "<=2025-12-31"), IF(_xlpm.usedCount=0, 2, MAX(2, _xlpm.usedCount/12*6*2)) ) -> 2 | I24: =IF(G24<H24,"X","O") -> O | J24: 213 | K24: KNAPP | L24: Sick | N24: =M24*$N$1 -> 0 | P24: 10 | Q24: =COUNTIF('ASRS parts replacement'!F:F,D24) -> 3
D25: 10200757 | H25: =_xlfn.LET( _xlpm.orderNum,#REF!, _xlpm.usedCount, COUNTIFS( 'ASRS parts replacement'!F:F, _xlpm.orderNum, 'ASRS parts replacement'!A:A, ">=2025-01-01", 'ASRS parts replacement'!A:A, "<=2025-12-31"), IF(_xlpm.usedCount=0, 2, MAX(2, _xlpm.usedCount/12*6*2)) ) -> 2 | N25: =M25*$N$1 -> 0 | O25: 2024.02.29 | P25: 100 | Q25: =COUNTIF('ASRS parts replacement'!F:F,D25) -> 0
C26: POWER SUPPLY UNIT, TDR-960-24V 40A | D26: 10446264 | E26: SUV : 1ea | F26: 67 | G26: 3 | H26: =_xlfn.LET( _xlpm.orderNum,#REF!, _xlpm.usedCount, COUNTIFS( 'ASRS parts replacement'!F:F, _xlpm.orderNum, 'ASRS parts replacement'!A:A, ">=2025-01-01", 'ASRS parts replacement'!A:A, "<=2025-12-31"), IF(_xlpm.usedCount=0, 2, MAX(2, _xlpm.usedCount/12*6*2)) ) -> 2 | I26: =IF(G26<H26,"X","O") -> O | J26: 124 | K26: KNAPP | L26: Mean Well | M26: 255.47 | N26: =M26*$N$1 -> 437364.64 | P26: 3 | Q26: =COUNTIF('ASRS parts replacement'!F:F,D26) -> 1
C27: POWER SUPPLY UNIT, TDR-960-48V 20A | D27: 10218312 | E27: SUV : 8ea | F27: 167 | G27: 4 | H27: =_xlfn.LET( _xlpm.orderNum,#REF!, _xlpm.usedCount, COUNTIFS( 'ASRS parts replacement'!F:F, _xlpm.orderNum, 'ASRS parts replacement'!A:A, ">=2025-01-01", 'ASRS parts replacement'!A:A, "<=2025-12-31"), IF(_xlpm.usedCount=0, 2, MAX(2, _xlpm.usedCount/12*6*2)) ) -> 2 | I27: =IF(G27<H27,"X","O") -> O | J27: 124 | K27: KNAPP | L27: Mean Well | M27: 255.47 | N27: =M27*$N$1 -> 437364.64 | P27: 3 | Q27: =COUNTIF('ASRS parts replacement'!F:F,D27) -> 0
C28: ACCESS CONCEPT LZYL=4510 LINKS 1E V2 ... | D28: 10609544_02_0001 | E28: OSR Rack | F28: 94 | G28: 10 | H28: =_xlfn.LET( _xlpm.orderNum,#REF!, _xlpm.usedCount, COUNTIFS( 'ASRS parts replacement'!F:F, _xlpm.orderNum, 'ASRS parts replacement'!A:A, ">=2025-01-01", 'ASRS parts replacement'!A:A, "<=2025-12-31"), IF(_xlpm.usedCount=0, 2, MAX(2, _xlpm.usedCount/12*6*2)) ) -> 2 | I28: =IF(G28<H28,"X","O") -> O | J28: 124 | M28: 516.15 | N28: =M28*$N$1 -> 883648.8 | P28: 3 | Q28: =COUNTIF('ASRS parts replacement'!F:F,D28) -> 10
C29: ACCESS CONCEPT EMERGENCY E -KPL, K_LOCK | D29: 10505322_01 | E29: OSR Rack | F29: 18 | G29: 5 | H29: =_xlfn.LET( _xlpm.orderNum,#REF!, _xlpm.usedCount, COUNTIFS( 'ASRS parts replacement'!F:F, _xlpm.orderNum, 'ASRS parts replacement'!A:A, ">=2025-01-01", 'ASRS parts replacement'!A:A, "<=2025-12-31"), IF(_xlpm.usedCount=0, 2, MAX(2, _xlpm.usedCount/12*6*2)) ) -> 2 | I29: =IF(G29<H29,"X","O") -> O | J29: 124 | M29: 405.55 | N29: =M29*$N$1 -> 694301.6 | P29: 2 | Q29: =COUNTIF('ASRS parts replacement'!F:F,D29) -> 0
C30: CHAIN TELL1490 TEL. -M, OSR_EVO | D30: 10395761_01_0016 | E30: OSR Shuttle | F30: 180 | G30: 12 | H30: =_xlfn.LET( _xlpm.orderNum,#REF!, _xlpm.usedCount, COUNTIFS( 'ASRS parts replacement'!F:F, _xlpm.orderNum, 'ASRS parts replacement'!A:A, ">=2025-01-01", 'ASRS parts replacement'!A:A, "<=2025-12-31"), IF(_xlpm.usedCount=0, 2, MAX(2, _xlpm.usedCount/12*6*2)) ) -> 2 | I30: =IF(G30<H30,"X","O") -> O | J30: C14 | K30: KNAPP | M30: 150.43 | N30: =M30*$N$1 -> 257536.16 | P30: 5 | Q30: =COUNTIF('ASRS parts replacement'!F:F,D30) -> 0
C31: Door safety switch, PILZ 506334 (506301+506308) | D31: 10217650 | E31: OSR Rack | F31: 99 | G31: 12 | H31: =_xlfn.LET( _xlpm.orderNum,#REF!, _xlpm.usedCount, COUNTIFS( 'ASRS parts replacement'!F:F, _xlpm.orderNum, 'ASRS parts replacement'!A:A, ">=2025-01-01", 'ASRS parts replacement'!A:A, "<=2025-12-31"), IF(_xlpm.usedCount=0, 2, MAX(2, _xlpm.usedCount/12*6*2)) ) -> 2 | I31: =IF(G31<H31,"X","O") -> O | J31: 223 | K31: KNAPP | L31: Pilz | M31: 121.08 | N31: =M31*$N$1 -> 207288.96 | P31: 10 | Q31: =COUNTIF('ASRS parts replacement'!F:F,D31) -> 3
C32: CURRENT COLLECTOR, 0815 2P1PH 35A REV... | D32: 10764610_01 | E32: OSR Shuttle | F32: 180 | G32: 104 | H32: =_xlfn.LET( _xlpm.orderNum,#REF!, _xlpm.usedCount, COUNTIFS( 'ASRS parts replacement'!F:F, _xlpm.orderNum, 'ASRS parts replacement'!A:A, ">=2025-01-01", 'ASRS parts replacement'!A:A, "<=2025-12-31"), IF(_xlpm.usedCount=0, 2, MAX(2, _xlpm.usedCount/12*6*2)) ) -> 2 | I32: =IF(G32<H32,"X","O") -> O | J32: 202 | K32: KNAPP | M32: 170.83 | N32: =M32*$N$1 -> 292460.96 | P32: 30 | Q32: =COUNTIF('ASRS parts replacement'!F:F,D32) -> 304
C33: Sideguide wheel_Vibration buffer | D33: 10634710_01 | E33: OSR Shuttle | F33: 360 | G33: 70 | H33: =_xlfn.LET( _xlpm.orderNum,#REF!, _xlpm.usedCount, COUNTIFS( 'ASRS parts replacement'!F:F, _xlpm.orderNum, 'ASRS parts replacement'!A:A, ">=2025-01-01", 'ASRS parts replacement'!A:A, "<=2025-12-31"), IF(_xlpm.usedCount=0, 2, MAX(2, _xlpm.usedCount/12*6*2)) ) -> 2 | I33: =IF(G33<H33,"X","O") -> O | J33: 242 | K33: KNAPP | N33: =M33*$N$1 -> 0 | P33: 100 | Q33: =COUNTIF('ASRS parts replacement'!F:F,D33) -> 0
C34: SIDE GUIDE WHEEL, COMPENSA EBG, OSR_EVO | D34: 10679338_01 | E34: OSR Shuttle | F34: 360 | G34: 110 | H34: =_xlfn.LET( _xlpm.orderNum,#REF!, _xlpm.usedCount, COUNTIFS( 'ASRS parts replacement'!F:F, _xlpm.orderNum, 'ASRS parts replacement'!A:A, ">=2025-01-01", 'ASRS parts replacement'!A:A, "<=2025-12-31"), IF(_xlpm.usedCount=0, 2, MAX(2, _xlpm.usedCount/12*6*2)) ) -> 2 | I34: =IF(G34<H34,"X","O") -> O | J34: 242 | K34: KNAPP | N34: =M34*$N$1 -> 0 | P34: 100 | Q34: =COUNTIF('ASRS parts replacement'!F:F,D34) -> 0
C35: Sideguide wheel_Bracket (Front left side, rear right side | D35: 10611156_02 | E35: OSR Shuttle | F35: 90 | G35: 40 | H35: =_xlfn.LET( _xlpm.orderNum,#REF!, _xlpm.usedCount, COUNTIFS( 'ASRS parts replacement'!F:F, _xlpm.orderNum, 'ASRS parts replacement'!A:A, ">=2025-01-01", 'ASRS parts replacement'!A:A, "<=2025-12-31"), IF(_xlpm.usedCount=0, 2, MAX(2, _xlpm.usedCount/12*6*2)) ) -> 2 | I35: =IF(G35<H35,"X","O") -> O | J35: 242 | K35: KNAPP | N35: =M35*$N$1 -> 0 | P35: 40 | Q35: =COUNTIF('ASRS parts replacement'!F:F,D35) -> 16
C36: Sideguide wheel_Bracket (Front right side, Rear left side | D36: 10611156_03 | E36: OSR Shuttle | F36: 90 | G36: 40 | H36: =_xlfn.LET( _xlpm.orderNum,#REF!, _xlpm.usedCount, COUNTIFS( 'ASRS parts replacement'!F:F, _xlpm.orderNum, 'ASRS parts replacement'!A:A, ">=2025-01-01", 'ASRS parts replacement'!A:A, "<=2025-12-31"), IF(_xlpm.usedCount=0, 2, MAX(2, _xlpm.usedCount/12*6*2)) ) -> 2 | I36: =IF(G36<H36,"X","O") -> O | J36: 242 | K36: KNAPP | N36: =M36*$N$1 -> 0 | P36: 40 | Q36: =COUNTIF('ASRS parts replacement'!F:F,D36) -> 32
